Workbook

Sheet Dashboard
A1: Retail Sales Dashboard
A4: Total Sales | E4: Total Profit | I4: Total Orders | M4: Avg Order Value
A5: =SUM('Cleaned Data'!$N$2:$N$651) -> 883903.36 | E5: =SUM('Cleaned Data'!$O$2:$O$651) -> 102358.47 | I5: =COUNTA('Cleaned Data'!$A$2:$A$651) -> 650 | M5: =AVERAGE('Cleaned Data'!$N$2:$N$651) -> 1359.8513

Sheet Raw Data
A1: Order ID | B1: Order Date | C1: Ship Date | D1: Customer Name | E1: Segment | F1: Region | G1: City | H1: Category | I1: Sub-Category | J1: Ship Mode | K1: Quantity | L1: Unit Price | M1: Discount | N1: Sales | O1: Profit
A2: ORD-100109 | B2: 24/09/2024 | C2: 26/09/2024 | D2: Yuki Ali | E2: Corporate | F2: West | G2: Pune | H2: Home & Kitchen | I2: Blender | J2: Second Class | K2: 4 | L2: 425.62 | M2: 0.15 | N2: 1447.11 | O2: -67.96
A3: ORD-100329 | B3: 26/11/2023 | C3: 29/11/2023 | D3: Grace Brown | E3: Consumer | F3: EAST | G3: Patna | H3: Office Supplies | I3: Printer Paper | J3: Standard Class | L3: 331.25 | N3: 331.25 | O3: 37.91
A4: ORD-100057 | B4: 2023-04-16 | C4: 2023-04-23 | D4: Noah Chen | E4: Corporate | F4: east | G4: Patna | H4: Home & Kitchen | I4: Toaster | J4: First Class | K4: 2 | L4: 1149.48 | M4: 0.15 | N4: 1954.12 | O4: 189.53
A5: ORD-100134 | B5: 2023-01-01 | C5: 2023-01-04 | D5: Raj Garcia | E5: Home Office | F5: NORTH | G5: Delhi | H5: Electronics | I5: Smartphone | J5: Standard Class | K5: 2 | L5: 28.81 | M5: 0.15 | N5: 48.98 | O5: -4.42
A6: ORD-100115 | B6: 08/05/2023 | C6: 08/09/2023 | D6: Anaya Ali | F6: East | G6: Bhubaneswar | H6: Electronics | I6: Smartwatch | J6: Same Day | K6: 5 | L6: 265.31 | M6: 0.15 | N6: 1127.57 | O6: 340.94
A7: ORD-100549 | B7: 10/07/2024 | C7: 10/10/2024 | D7: Ivan Petrov | E7: Home Office | F7: WEST | G7: Pune | H7: clothing | I7: T-Shirt | J7: Second Class | K7: 2 | L7: 682.48 | M7: 0 | N7: 1364.96 | O7: 366.17
A8: ORD-100542 | B8: 2023-12-17 | C8: 2023-12-24 | D8: wei wang | E8: Corporate | F8: east | G8: Kolkata | H8: Clothing | I8: Cap | J8: Second Class | L8: 797.58 | N8: 797.58 | O8: 1.76
A9: ORD-100343 | B9: 20-08-2024 | C9: 26-08-2024 | E9: Corporate | F9: WEST | G9: Mumbai | H9: OFFICE SUPPLIES | I9: Binder | J9: Standard Class | K9: 5 | L9: 767.54 | N9: 3837.7 | O9: 396.96
A10: ORD-100277 | B10: 06-11-2024 | C10: 11-11-2024 | D10: amara khan | E10: Home Office | F10: WEST | G10: Ahmedabad | H10: Clothing | I10: T-Shirt | J10: Standard Class | K10: 2 | L10: 133.84 | N10: 267.68 | O10: -25.53
A11: ORD-100232 | B11: 09-05-2024 | C11: 14-05-2024 | D11: Noah Okafor | E11: Home Office | F11: Nort | G11: Delhi | H11: Furniture | I11: Office Chair | J11: Standard Class | L11: 609.66 | N11: 609.66 | O11: 150.14
A12: ORD-100563 | B12: 2023-11-24 | C12: 2023-11-25 | D12: Amara Patel | E12: Consumer | F12: South | G12: Bengaluru | H12: electronics | I12: Tablet | J12: First Class | K12: 2 | L12: 1071.37 | N12: 2142.74
A13: ORD-100490 | B13: 04/04/2023 | C13: 04/11/2023 | D13: carlos johnson | E13: Consumer | F13: West | G13: Mumbai | H13: Furniture | I13: Bookshelf | J13: Same Day | K13: 1 | L13: 941.12 | M13: 0.05 | N13: 894.06 | O13: -34.3
A14: ORD-100281 | B14: May 06, 2023 | C14: May 08, 2023 | D14: Hassan Okafor | E14: Home Office | F14: east | G14: Patna | H14: Furniture | I14: Desk | J14: Standard Class | K14: 2 | L14: 715.98 | M14: 0.15 | N14: 1217.17 | O14: 394.91
A15: ORD-100023 | B15: 2024-07-31 | C15: 2024-08-06 | F15: South | G15: Chennai | H15: CLOTHING | I15: Jeans | J15: Same Day | K15: 1 | L15: 1088.78 | M15: 0.2 | N15: 871.02 | O15: 252.67
A16: ORD-100419 | B16: Jun 19, 2024 | C16: Jun 26, 2024 | D16: Ivan Johnson | E16: Corporate | F16: West | G16: Ahmedabad | H16: Clothing | I16: Jacket | J16: Standard Class | K16: 4 | L16: 994.68 | M16: 0.15 | N16: 3381.91 | O16: 325.15
A17: ORD-100452 | B17: 04/19/2023 | C17: 04/23/2023 | D17: Amara Brown | E17: Corporate | F17: NORTH | G17: Delhi | H17: Electronics | I17: Headphones | J17: Standard Class | K17: 2 | L17: 281.89 | N17: 563.78 | O17: 171.9
A18: ORD-100110 | B18: 11/07/2023 | C18: 14/07/2023 | D18: Grace Sharma | F18: West | G18: Mumbai | H18: Home & Kitchen | I18: Cookware Set | J18: Second Class | K18: 2 | L18: 590.12 | M18: 0.05 | N18: 1121.23 | O18: -13.67
A19: ORD-100229 | B19: 2023-11-28 | C19: 2023-12-05 | E19: Home Office | F19: east | G19: Bhubaneswar | H19: Office Supplies | I19: Notebook | J19: Standard Class | K19: 3 | L19: 363.84 | M19: 0.2 | N19: 873.22 | O19: 68.31
A20: ORD-100352 | B20: 01-08-2023 | C20: 06-08-2023 | E20: Consumer | F20: North | G20: Delhi | H20: HOME & KITCHEN | I20: Vacuum Cleaner | J20: Standard Class | K20: 5 | L20: 543.87 | M20: 0.1 | N20: 2447.41 | O20: 458.86
A21: ORD-100568 | B21: 24/02/2024 | C21: 29/02/2024 | D21: Grace Johnson | E21: Consumer | F21: South | G21: Chennai | H21: home & kitchen | I21: Vacuum Cleaner | J21: Standard Class | K21: 1 | L21: 138.08 | M21: 0 | N21: 138.08
A22: ORD-100610 | B22: 05/21/2023 | C22: 05/24/2023 | D22: Tom Okafor | F22: East | G22: Bhubaneswar | H22: home & kitchen | I22: Air Fryer | J22: Standard Class | K22: 1 | L22: 367.5 | N22: 367.5 | O22: 42.42
A23: ORD-100235 | B23: 30-06-2024 | C23: 01-07-2024 | D23: Maria Tanaka | F23: EAST | G23: Kolkata | H23: OFFICE SUPPLIES | I23: Printer Paper | J23: First Class | K23: 2 | L23: 856.91 | N23: 1713.82 | O23: 179.97
A24: ORD-100202 | B24: 2023-04-07 | C24: 2023-04-12 | D24: Raj Okafor | E24: Home Office | F24: West | G24: Mumbai | H24: clothing | I24: Jeans | J24: Standard Class | K24: 1 | L24: 243.02 | N24: 243.02 | O24: 44.5
A25: ORD-100386 | B25: 2023-05-17 | C25: 2023-05-22 | D25: Priya Petrov | E25: Consumer | F25: SOUTH | G25: Bengaluru | H25: home & kitchen | I25: Cookware Set | J25: Standard Class | K25: 2 | L25: 94.77 | N25: 189.54 | O25: 59.01
A26: ORD-100551 | B26: 02-06-2024 | C26: 08-06-2024 | D26: Aisha Novak | E26: Consumer | F26: SOUTH | G26: Chennai | H26: Office Supplies | I26: Notebook | J26: Second Class | K26: 1 | L26: 231.8 | M26: 0.1 | N26: 208.62 | O26: -12.1
A27: ORD-100351 | B27: 07/07/2023 | C27: 13/07/2023 | D27: Diego Sharma | E27: Home Office | F27: South | G27: Hyderabad | H27: HOME & KITCHEN | I27: Toaster | J27: Standard Class | L27: 464.67 | N27: 464.67 | O27: 65.97
A28: ORD-100470 | B28: 22-02-2024 | C28: 28-02-2024 | D28: Carlos Lee | E28: Home Office | F28: West | G28: Mumbai | H28: Clothing | I28: Jeans | J28: Second Class | K28: 2 | L28: 1111.23 | M28: 0.05 | N28: 2111.34 | O28: -133.69
A29: ORD-100191 | B29: 09-10-2023 | C29: 13-10-2023 | D29: Maria Martin | E29: Corporate | F29: North | G29: Delhi | H29: Clothing | I29: Jacket | J29: First Class | K29: 4 | L29: 593.35 | M29: 0.2 | N29: 1898.72 | O29: 259.33
A30: ORD-100465 | B30: 10/11/2023 | C30: 10/16/2023 | D30: Wei Tanaka | E30: Home Office | F30: West | G30: Pune | H30: home & kitchen | I30: Cookware Set | J30: Same Day | K30: 5 | L30: 75.01 | M30: 0 | N30: 375.05 | O30: 109.17
A31: ORD-100600 | B31: Oct 27, 2023 | C31: Oct 29, 2023 | D31: Maria Okafor | F31: west | G31: Mumbai | H31: Furniture | I31: Dining Table | J31: First Class | K31: 5 | L31: 449.67 | M31: 0.1 | N31: 2023.51 | O31: 345.96
A32: ORD-100589 | B32: 17-10-2023 | C32: 19-10-2023 | D32: Olga Smith | E32: Home Office | F32: Nort | G32: Delhi | H32: office supplies | I32: Notebook | J32: Same Day | K32: 2 | L32: 630.59 | M32: 0.2 | N32: 1008.94 | O32: -87.81
A33: ORD-100586 | B33: 2024-09-18 | C33: 2024-09-19 | D33: Lucas Ali | E33: Corporate | F33: east | G33: Bhubaneswar | H33: Furniture | I33: Desk | J33: First Class | K33: 3 | L33: 822.45 | M33: 0.15 | N33: 2097.25 | O33: 323.81
A34: ORD-100357 | B34: Dec 11, 2024 | C34: Dec 13, 2024 | D34: Arjun Brown | E34: Consumer | F34: North | G34: Chandigarh | H34: home & kitchen | I34: Vacuum Cleaner | J34: Standard Class | K34: 5 | L34: 815.09 | N34: 4075.45 | O34: -375.18
A35: ORD-100294 | B35: 2024-04-27 | C35: 2024-05-03 | D35: Anaya Brown | E35: Consumer | F35: West | G35: Mumbai | H35: Electronics | I35: Laptop | J35: Second Class | K35: 1 | L35: 988.72 | M35: 0.15 | N35: 840.41 | O35: 180.11
A36: ORD-100442 | B36: Dec 19, 2024 | C36: Dec 22, 2024 | D36: Fatima Petrov | E36: Home Office | F36: west | G36: Pune | H36: OFFICE SUPPLIES | I36: Printer Paper | J36: Same Day | K36: 2 | L36: 54.11 | M36: 0.2 | N36: 1298.7 | O36: -4.36
A37: ORD-100360 | B37: 2023-11-15 | C37: 2023-11-17 | D37: Sofia Petrov | E37: Home Office | F37: south | G37: Hyderabad | H37: Furniture | I37: Dining Table | J37: Same Day | K37: 1 | L37: 514.36 | M37: 0.15 | N37: 437.21 | O37: 44.47
A38: ORD-100401 | B38: 30/03/2024 | C38: 06/04/2024 | D38: Noah Okafor | E38: Home Office | F38: East | G38: Patna | H38: Electronics | I38: Smartphone | J38: Second Class | K38: 2 | L38: 579.11 | M38: 0.2 | N38: 926.58 | O38: 134.01
A39: ORD-100417 | B39: 03/09/2024 | C39: 05/09/2024 | D39: Isabella Said | E39: Home Office | F39: South | G39: Chennai | H39: Clothing | I39: Jacket | J39: Second Class | K39: 5 | L39: 988.5 | M39: 0.2 | N39: 3954 | O39: -127.6
A40: ORD-100098 | B40: 2024-03-20 | C40: 2024-03-26 | D40: Omar Khan | E40: Corporate | F40: North | G40: Delhi | H40: electronics | I40: Bluetooth Speaker | J40: First Class | K40: 2 | L40: 103.81 | N40: 207.62 | O40: 63.44
A41: ORD-100441 | B41: Dec 13, 2024 | C41: Dec 17, 2024 | D41: Hassan Chen | E41: Consumer | F41: SOUTH | G41: Bengaluru | H41: FURNITURE | I41: Desk | J41: Same Day | L41: 41.93 | M41: 0.2 | N41: 33.54 | O41: 9.88
A42: ORD-100376 | B42: 03/07/2023 | C42: 04/07/2023 | D42: Lucas Brown | F42: West | G42: Mumbai | H42: Clothing | I42: Jeans | J42: Same Day | K42: 1 | L42: 119.78 | M42: 0.15 | N42: 101.81 | O42: -8.62
A43: ORD-100228 | B43: Jan 02, 2023 | C43: Jan 03, 2023 | E43: Consumer | F43: west | G43: Ahmedabad | H43: Clothing | I43: Jeans | J43: Second Class | K43: 2 | L43: 851.76 | M43: 0.05 | N43: 1618.34 | O43: 455.78
A44: ORD-100383 | B44: 22-11-2023 | C44: 29-11-2023 | D44: Mei Novak | F44: EAST | G44: Bhubaneswar | H44: HOME & KITCHEN | I44: Vacuum Cleaner | J44: Standard Class | K44: 1 | L44: 1076.4 | M44: 0.05 | N44: 1022.58 | O44: 170.3
A45: ORD-100384 | B45: 03/25/2024 | C45: 03/28/2024 | D45: Lucas Ali | E45: Corporate | F45: East | G45: Bhubaneswar | H45: Furniture | I45: Dining Table | J45: Second Class | K45: 5 | L45: 849.61 | M45: 0.05 | N45: 4035.65 | O45: 750.78
A46: ORD-100280 | B46: 13-07-2023 | C46: 20-07-2023 | D46: Anaya Okafor | E46: Consumer | F46: South | G46: Hyderabad | H46: home & kitchen | I46: Toaster | J46: Standard Class | K46: 3 | L46: 1182.03 | M46: 0.15 | N46: 3014.18 | O46: 365.44
A47: ORD-100141 | B47: 02-05-2024 | C47: 05-05-2024 | D47: Zara Sharma | E47: Corporate | F47: West | G47: Mumbai | H47: Home & Kitchen | I47: Toaster | J47: Same Day | L47: 689.39 | M47: 0.05 | N47: 654.92 | O47: 214.27
A48: ORD-100636 | B48: 22/05/2023 | C48: 23/05/2023 | D48: Tom Kim | E48: Consumer | F48: east | G48: Bhubaneswar | H48: HOME & KITCHEN | I48: Vacuum Cleaner | J48: First Class | K48: 1 | L48: 999 | M48: 0.1 | N48: 899.1 | O48: 155.47
A49: ORD-100259 | B49: 2023-05-29 | C49: 2023-05-31 | D49: Kenji Johnson | E49: Corporate | F49: South | G49: Hyderabad | H49: Electronics | I49: Tablet | J49: Same Day | L49: 69.94 | M49: 0.15 | N49: 59.45 | O49: 3.65
A50: ORD-100099 | B50: 2024-02-12 | C50: 2024-02-13 | D50: Omar Rossi | E50: Home Office | F50: Nort | G50: Chandigarh | H50: furniture | I50: Dining Table | J50: Standard Class | K50: 2 | L50: 903.94 | N50: 1807.88 | O50: 433.93
A51: ORD-100520 | B51: Jul 31, 2023 | C51: Aug 02, 2023 | D51: Grace Khan | F51: west | G51: Ahmedabad | H51: CLOTHING | I51: T-Shirt | J51: Standard Class | K51: 1 | L51: 414.13 | M51: 0.1 | N51: 372.72 | O51: 115.81
A52: ORD-100070 | B52: 11/06/2023 | C52: 17/06/2023 | D52: Yuki Johnson | E52: Consumer | F52: EAST | G52: Kolkata | H52: electronics | I52: Smartwatch | J52: Standard Class | K52: 3 | L52: 1070.14 | N52: 3210.42 | O52: 823.25
A53: ORD-100155 | B53: 07/24/2023 | C53: 07/31/2023 | D53: Lucas Patel | E53: Corporate | F53: North | G53: Delhi | H53: Office Supplies | I53: Notebook | J53: Second Class | K53: 1 | L53: 599.8 | M53: 0.2 | N53: 479.84 | O53: 70.37
A54: ORD-100603 | B54: 2024-10-15 | C54: 2024-10-16 | D54: Raj Smith | E54: Corporate | F54: East | G54: Kolkata | H54: FURNITURE | I54: Sofa | J54: First Class | K54: 3 | L54: 991.15 | M54: 0.2 | N54: 2378.76 | O54: 648.08
A55: ORD-100387 | B55: 05/14/2024 | C55: 05/15/2024 | D55: Grace Tanaka | E55: Consumer | F55: west | G55: Pune | H55: Furniture | I55: Desk | J55: Standard Class | K55: 1 | L55: 1122.82 | M55: 0.2 | N55: 898.26 | O55: 270.01
A56: ORD-100140 | B56: Jan 14, 2024 | C56: Jan 16, 2024 | D56: Liam Tanaka | E56: Home Office | F56: EAST | G56: Patna | H56: electronics | I56: Bluetooth Speaker | J56: Standard Class | K56: 5 | L56: 225.93 | M56: 0.15 | N56: 960.2 | O56: -69.39
A57: ORD-100013 | B57: 02/22/2023 | C57: 02/23/2023 | D57: Anaya Kim | E57: Corporate | F57: south | G57: Hyderabad | H57: Office Supplies | I57: Binder | J57: First Class | L57: 305.09 | N57: 305.09 | O57: 104.01
A58: ORD-100060 | B58: 2024-02-25 | C58: 2024-02-28 | D58: Sofia Tanaka | F58: South | G58: Chennai | H58: Furniture | I58: Dining Table | J58: First Class | K58: 2 | L58: 866.81 | M58: 0 | N58: 1733.62 | O58: 243.24
A59: ORD-100467 | B59: 26-01-2023 | C59: 29-01-2023 | D59: Mei Brown | E59: Home Office | F59: West | G59: Pune | H59: Electronics | I59: Bluetooth Speaker | J59: Second Class | K59: 5 | L59: 1051.64 | M59: 0.05 | N59: 4995.29 | O59: 1619.05
A60: ORD-100392 | B60: 2024-06-06 | C60: 2024-06-10 | D60: Aisha Khan | E60: Home Office | F60: east | G60: Patna | H60: FURNITURE | I60: Bookshelf | J60: Standard Class | K60: 4 | L60: 514.16 | M60: 0 | N60: 2056.64 | O60: 181.26
A61: ORD-100221 | B61: 18/11/2024 | C61: 20/11/2024 | D61: Wei Johnson | F61: Nort | G61: Lucknow | H61: Clothing | I61: T-Shirt | J61: Standard Class | K61: 3 | L61: 1140.49 | M61: 0.05 | N61: 3250.4 | O61: 150.18
A62: ORD-100576 | B62: 24-04-2023 | C62: 01-05-2023 | D62: Raj Brown | E62: Consumer | F62: NORTH | G62: Chandigarh | H62: furniture | I62: Bookshelf | J62: First Class | K62: 3 | L62: 814.46 | M62: 0.05 | N62: 2321.21 | O62: 397.54
A63: ORD-100153 | B63: 18-05-2023 | C63: 21-05-2023 | D63: Amara Wang | F63: West | G63: Mumbai | H63: Home & Kitchen | I63: Air Fryer | J63: First Class | K63: 4 | L63: 523.23 | N63: 2092.92 | O63: 5.84
A64: ORD-100485 | B64: 06/19/2024 | C64: 06/25/2024 | D64: Maria Rossi | F64: south | G64: Bengaluru | H64: Electronics | I64: Smartphone | J64: Same Day | K64: 5 | L64: 741.7 | M64: 0.15 | N64: 3152.22 | O64: 735.19
A65: ORD-100411 | B65: 26/08/2023 | C65: 28/08/2023 | D65: Arjun Garcia | E65: Home Office | F65: South | G65: Bengaluru | H65: furniture | I65: Sofa | J65: Same Day | K65: 1 | L65: 1062.82 | M65: 0 | N65: 1062.82 | O65: 269.33
A66: ORD-100629 | B66: 2024-06-13 | C66: 2024-06-18 | D66: Kenji Okafor | E66: Consumer | F66: East | G66: Kolkata | H66: Home & Kitchen | I66: Vacuum Cleaner | J66: Same Day | K66: 3 | L66: 444.72 | N66: 1334.16 | O66: 426.7
A67: ORD-100624 | B67: 2023-11-30 | C67: 2023-12-07 | D67: Liam Martin | E67: Consumer | F67: east | G67: Bhubaneswar | H67: Furniture | I67: Bookshelf | J67: Second Class | K67: 2 | L67: 298.55 | M67: 0 | N67: 597.1 | O67: -23.45
A68: ORD-100429 | B68: 12/03/2023 | C68: 12/05/2023 | D68: Ethan Brown | F68: EAST | G68: Bhubaneswar | H68: Electronics | I68: Headphones | J68: Same Day | K68: 4 | L68: 827.51 | N68: 3310.04 | O68: 565.39
A69: ORD-100521 | B69: 04/07/2024 | C69: 11/07/2024 | D69: Ethan Sharma | E69: Corporate | F69: WEST | G69: Pune | H69: ELECTRONICS | I69: Laptop | J69: Standard Class | K69: 1 | L69: 329.41 | M69: 0.2 | N69: 263.53 | O69: 68.19
A70: ORD-100439 | B70: 2023-03-20 | C70: 2023-03-22 | D70: Tom Smith | E70: Consumer | F70: west | G70: Pune | H70: clothing | I70: Jacket | J70: Standard Class | K70: 1 | L70: 217.13 | M70: 0.1 | N70: 195.42
A71: ORD-100445 | B71: 2024-08-03 | C71: 2024-08-09 | D71: Emma Fernandez | E71: Consumer | F71: West | G71: Mumbai | H71: Home & Kitchen | I71: Cookware Set | J71: Same Day | K71: 3 | L71: 369.47 | M71: 0.1 | N71: 997.57 | O71: 136.62
A72: ORD-100385 | B72: Jan 11, 2023 | C72: Jan 15, 2023 | D72: Ivan Garcia | E72: Consumer | F72: north | G72: Chandigarh | H72: Electronics | I72: Bluetooth Speaker | J72: Same Day | K72: 3 | L72: 667.22 | M72: 0.15 | N72: 1701.41
A73: ORD-100200 | B73: 14/10/2024 | C73: 18/10/2024 | D73: Liam Lee | E73: Corporate | F73: west | G73: Mumbai | H73: Furniture | I73: Office Chair | J73: Second Class | K73: 2 | L73: 168.27 | M73: 0 | N73: 336.54 | O73: 113.2
A74: ORD-100589 | B74: 17-10-2023 | C74: 19-10-2023 | D74: Olga Smith | E74: Home Office | F74: Nort | G74: Delhi | H74: office supplies | I74: Notebook | J74: Same Day | K74: 2 | L74: 630.59 | M74: 0.2 | N74: 1008.94 | O74: -87.81
A75: ORD-100627 | B75: 2024-05-13 | C75: 2024-05-17 | D75: Kenji Wang | F75: South | G75: Chennai | H75: Furniture | I75: Office Chair | J75: Standard Class | K75: 2 | L75: 1084.88 | M75: 0.1 | N75: 1952.78 | O75: 20.34
A76: ORD-100633 | B76: 2024-09-30 | C76: 2024-10-04 | D76: Isabella Chen | E76: Consumer | F76: west | G76: Pune | H76: Home & Kitchen | I76: Vacuum Cleaner | J76: Same Day | K76: 3 | L76: 101.95 | M76: 0.05 | N76: 290.56 | O76: 24.02
A77: ORD-100571 | B77: 30-07-2023 | C77: 01-08-2023 | D77: Raj Said | E77: Home Office | F77: EAST | G77: Bhubaneswar | H77: Office Supplies | I77: Printer Paper | J77: First Class | K77: 5 | L77: 164.07 | M77: 0.2 | N77: 656.28 | O77: 96.27
A78: ORD-100159 | B78: 30-01-2024 | C78: 01-02-2024 | D78: Nina Lee | E78: Corporate | F78: WEST | G78: Ahmedabad | H78: Furniture | I78: Sofa | J78: Second Class | K78: 4 | L78: 798.13 | N78: 3192.52 | O78: 900.23
A79: ORD-100252 | B79: 15-07-2023 | C79: 18-07-2023 | D79: Zara Khan | E79: Consumer | F79: East | G79: Patna | H79: FURNITURE | I79: Bookshelf | J79: Same Day | K79: 1 | L79: 1161.18 | N79: 1161.18
A80: ORD-100637 | B80: 2023-09-04 | C80: 2023-09-08 | D80: Carlos Sharma | E80: Consumer | F80: West | G80: Mumbai | H80: Clothing | I80: Jeans | J80: Same Day | K80: 3 | L80: 801.18 | M80: 0.05 | N80: 2283.36 | O80: -117.7
A81: ORD-100496 | B81: 12-11-2023 | C81: 19-11-2023 | D81: Zara Patel | E81: Home Office | F81: south | G81: Chennai | H81: office supplies | I81: Pen Set | J81: First Class | K81: 1 | L81: 1053.25 | M81: 0.05 | N81: 1000.59 | O81: 70.73
A82: ORD-100053 | B82: 2023-01-08 | C82: 2023-01-12 | D82: Emma Garcia | E82: Home Office | F82: EAST | G82: Kolkata | H82: Furniture | I82: Bookshelf | J82: Same Day | K82: 3 | L82: 350.89 | M82: 0 | N82: 1052.67 | O82: 82.83
A83: ORD-100646 | B83: 23/08/2024 | C83: 29/08/2024 | D83: Hassan Rossi | F83: WEST | G83: Ahmedabad | H83: Furniture | I83: Bookshelf | J83: First Class | K83: 2 | L83: 747.18 | M83: 0.15 | N83: 1270.21 | O83: 313.59
A84: ORD-100408 | B84: 2023-08-05 | C84: 2023-08-09 | D84: Sofia Fernandez | E84: Consumer | F84: west | G84: Ahmedabad | H84: FURNITURE | I84: Desk | J84: Standard Class | K84: 1 | L84: 628.19 | M84: 0.05 | N84: 596.78 | O84: 66.12
A85: ORD-100605 | B85: 05-04-2023 | C85: 06-04-2023 | D85: Anaya Khan | E85: Corporate | F85: West | G85: Ahmedabad | H85: Electronics | I85: Tablet | J85: Second Class | K85: 1 | L85: 572.47 | M85: 0.2 | N85: 457.98 | O85: 157
A86: ORD-100256 | B86: 10/05/2023 | C86: 10/10/2023 | D86: sofia johnson | E86: Corporate | F86: East | G86: Patna | H86: Clothing | I86: Sneakers | J86: Standard Class | K86: 2 | L86: 251.36 | N86: 502.72 | O86: 62.81
A87: ORD-100320 | B87: 24-11-2024 | C87: 29-11-2024 | D87: Nina Martin | F87: west | G87: Ahmedabad | H87: Furniture | I87: Sofa | J87: Same Day | K87: 2 | L87: 538.17 | M87: 0.1 | N87: 968.71 | O87: 87.71
A88: ORD-100022 | B88: 12/08/2024 | C88: 16/08/2024 | D88: Mei Ali | F88: West | G88: Ahmedabad | H88: CLOTHING | I88: Cap | J88: Same Day | K88: 1 | L88: 1028.79 | N88: 1028.79 | O88: 243.19
A89: ORD-100300 | B89: 2023-11-17 | C89: 2023-11-18 | D89: Amara Kim | E89: Home Office | F89: South | G89: Bengaluru | H89: electronics | I89: Laptop | J89: Same Day | K89: 5 | L89: 174.45 | M89: 0 | N89: 872.25 | O89: 153.36
A90: ORD-100507 | B90: Oct 10, 2024 | C90: Oct 14, 2024 | D90: Liam Wang | E90: Corporate | F90: South | G90: Hyderabad | H90: Furniture | I90: Office Chair | J90: Standard Class | K90: 1 | L90: 155.64 | M90: 0.05 | N90: 147.86 | O90: 39.81
A91: ORD-100138 | B91: May 09, 2024 | C91: May 15, 2024 | E91: Corporate | F91: NORTH | G91: Lucknow | H91: HOME & KITCHEN | I91: Blender | J91: First Class | K91: 4 | L91: 714.87 | M91: 0.2 | N91: 2287.58 | O91: 687.16
A92: ORD-100640 | B92: 05/09/2024 | C92: 05/16/2024 | D92: Lucas Patel | E92: Home Office | F92: EAST | G92: Patna | H92: OFFICE SUPPLIES | I92: Binder | J92: Same Day | K92: 4 | L92: 407.93 | M92: 0 | N92: 1631.72 | O92: 123.7
A93: ORD-100606 | B93: Oct 09, 2023 | C93: Oct 15, 2023 | D93: ethan novak | E93: Consumer | F93: North | G93: Lucknow | H93: home & kitchen | I93: Toaster | J93: Standard Class | K93: 1 | L93: 604.98 | M93: 0.15 | N93: 514.23 | O93: 68.15
A94: ORD-100148 | B94: 10/11/2023 | C94: 10/14/2023 | D94: Zara Ali | E94: Corporate | F94: WEST | G94: Mumbai | H94: ELECTRONICS | I94: Laptop | J94: Same Day | K94: 3 | L94: 770.51 | N94: 2311.53 | O94: 606.65
A95: ORD-100328 | B95: 27-11-2024 | C95: 01-12-2024 | D95: Anaya Patel | E95: Consumer | F95: SOUTH | G95: Chennai | H95: Electronics | I95: Headphones | J95: Second Class | L95: 331.6 | M95: 0.1 | N95: 298.44 | O95: 69.43
A96: ORD-100501 | B96: 26/06/2023 | C96: 29/06/2023 | D96: Emma Rossi | E96: Corporate | F96: West | G96: Mumbai | H96: furniture | I96: Sofa | J96: Same Day | K96: 1 | L96: 792.04 | M96: 0.05 | N96: 752.44 | O96: 156.6
A97: ORD-100179 | B97: 01/10/2024 | C97: 01/15/2024 | D97: Anaya Chen | E97: Corporate | F97: East | G97: Patna | H97: Home & Kitchen | I97: Air Fryer | J97: Second Class | K97: 2 | L97: 455.11 | M97: 0.15 | N97: 773.69 | O97: 63.93
A98: ORD-100578 | B98: 01/11/2024 | C98: 01/18/2024 | D98: Ethan Petrov | E98: Home Office | F98: WEST | G98: Ahmedabad | H98: Clothing | I98: T-Shirt | J98: Standard Class | K98: 3 | L98: 837.74 | M98: 0.1 | N98: 2261.9 | O98: 40.07
A99: ORD-100278 | B99: 05/27/2024 | C99: 06/03/2024 | D99: Sofia Martin | E99: Consumer | F99: South | G99: Hyderabad | H99: OFFICE SUPPLIES | I99: Binder | J99: Second Class | K99: 4 | L99: 425.88 | N99: 1703.52 | O99: -4
A100: ORD-100132 | B100: 01/27/2023 | C100: 01/30/2023 | D100: John Kim | E100: Home Office | F100: west | G100: Ahmedabad | H100: Office Supplies | I100: Binder | J100: First Class | K100: 4 | L100: 469.12 | M100: 0.05 | N100: 1782.66 | O100: 623.61
...

Sheet Cleaning Log
A1: Data Cleaning Log
A3: Original raw rows: 670
A4: Removed fully blank rows: 5
A5: Removed exact duplicate rows: 15
A6: Rows remaining after removing blanks/duplicates: 650
A7: Corrected 29 misspelled Region values ('Nort' -> 'North')
A8: Standardized casing/whitespace in Customer Name, Region, Category, City, Segment, Ship Mode, Sub-Category
A9: Filled missing Customer Name (36 rows) with 'Unknown Customer'
A10: Filled missing Segment (163 rows) with 'Unknown'
A11: Parsed Order Date and Ship Date from 5 mixed formats into a single consistent date format
A12: Ship Date left blank for 21 rows with no recorded ship date (flagged for review, not guessed)
A13: Filled missing Quantity (65 rows) with the median quantity for that product Category
... A38: Order ORD-100029: Profit 1194.71 -> capped to 993.15

Sheet Cleaned Data
A1: Order ID | B1: Order Date | C1: Ship Date | D1: Customer Name | E1: Segment | F1: Region | G1: City | H1: Category | I1: Sub-Category | J1: Ship Mode | K1: Quantity | L1: Unit Price | M1: Discount | N1: Sales | O1: Profit | P1: Order Month | Q1: Profit Margin % | R1: Outlier Flag | T1: Outlier thresholds (IQR method)
A2: ORD-100134 | B2: 44927 | C2: 44930 | D2: Raj Garcia | E2: Home Office | F2: North | G2: Delhi | H2: Electronics | I2: Smartphone | J2: Standard Class | K2: 2 | L2: 28.81 | M2: 0.15 | N2: 48.98 | O2: -4.42 | P2: =TEXT(B2,"mmm-yyyy") -> Jan-2023 | Q2: =IFERROR(O2/N2,"") -> -0.090240915 | R2: =IF(OR(N2>$U$3,N2<$U$2),"Sales Outlier",IF(OR(O2>$U$6,O2<$U$4),"Profit Outlier","")) | T2: Sales lower bound | U2: =QUARTILE(N2:N651,1)-3*(QUARTILE(N2:N651,3)-QUARTILE(N2:N651,1)) -> -3842.32
A3: ORD-100228 | B3: 44928 | C3: 44929 | D3: Unknown Customer | E3: Consumer | F3: West | G3: Ahmedabad | H3: Clothing | I3: Jeans | J3: Second Class | K3: 2 | L3: 851.76 | M3: 0.05 | N3: 1618.34 | O3: 455.78 | P3: =TEXT(B3,"mmm-yyyy") -> Jan-2023 | Q3: =IFERROR(O3/N3,"") -> 0.28163427 | R3: =IF(OR(N3>$U$3,N3<$U$2),"Sales Outlier",IF(OR(O3>$U$6,O3<$U$4),"Profit Outlier","")) | T3: Sales upper bound | U3: =QUARTILE(N2:N651,3)+3*(QUARTILE(N2:N651,3)-QUARTILE(N2:N651,1)) -> 6212.69
A4: ORD-100495 | B4: 44930 | C4: 44933 | D4: Mei Khan | E4: Consumer | F4: South | G4: Hyderabad | H4: Home & Kitchen | I4: Toaster | J4: Standard Class | K4: 2 | L4: 764.18 | M4: 0 | N4: 1528.36 | O4: 486.97 | P4: =TEXT(B4,"mmm-yyyy") -> Jan-2023 | Q4: =IFERROR(O4/N4,"") -> 0.31862258 | R4: =IF(OR(N4>$U$3,N4<$U$2),"Sales Outlier",IF(OR(O4>$U$6,O4<$U$4),"Profit Outlier","")) | T4: Profit lower bound | U4: =QUARTILE(O2:O651,1)-3*(QUARTILE(O2:O651,3)-QUARTILE(O2:O651,1)) -> -733.2225
A5: ORD-100082 | B5: 44932 | C5: 44937 | D5: Emma Petrov | E5: Unknown | F5: West | G5: Pune | H5: Office Supplies | I5: Pen Set | J5: Second Class | K5: 1 | L5: 819.02 | M5: 0.05 | N5: 778.07 | O5: 149.97 | P5: =TEXT(B5,"mmm-yyyy") -> Jan-2023 | Q5: =IFERROR(O5/N5,"") -> 0.19274615 | R5: =IF(OR(N5>$U$3,N5<$U$2),"Sales Outlier",IF(OR(O5>$U$6,O5<$U$4),"Profit Outlier","")) | U5: =QUARTILE(O2:O651,1)-3*(QUARTILE(O2:O651,3)-QUARTILE(O2:O651,1)) -> -733.2225
A6: ORD-100101 | B6: 44932 | C6: 44935 | D6: Maria Kim | E6: Unknown | F6: West | G6: Pune | H6: Furniture | I6: Sofa | J6: Standard Class | K6: 4 | L6: 436.04 | M6: 0 | N6: 1744.16 | O6: 262.75 | P6: =TEXT(B6,"mmm-yyyy") -> Jan-2023 | Q6: =IFERROR(O6/N6,"") -> 0.15064558 | R6: =IF(OR(N6>$U$3,N6<$U$2),"Sales Outlier",IF(OR(O6>$U$6,O6<$U$4),"Profit Outlier","")) | T6: Profit upper bound | U6: =QUARTILE(O2:O651,3)+3*(QUARTILE(O2:O651,3)-QUARTILE(O2:O651,1)) -> 993.1525
A7: ORD-100210 | B7: 44933 | C7: 44936 | D7: Raj Brown | E7: Home Office | F7: East | G7: Patna | H7: Home & Kitchen | I7: Blender | J7: Second Class | K7: 2 | L7: 1192.13 | M7: 0.1 | N7: 2145.83 | O7: 279.11 | P7: =TEXT(B7,"mmm-yyyy") -> Jan-2023 | Q7: =IFERROR(O7/N7,"") -> 0.13007088 | R7: =IF(OR(N7>$U$3,N7<$U$2),"Sales Outlier",IF(OR(O7>$U$6,O7<$U$4),"Profit Outlier",""))
A8: ORD-100532 | B8: 44933 | C8: 44938 | D8: John Smith | E8: Home Office | F8: West | G8: Mumbai | H8: Home & Kitchen | I8: Toaster | J8: Second Class | K8: 1 | L8: 484.75 | M8: 0.1 | N8: 436.28 | O8: 71.1 | P8: =TEXT(B8,"mmm-yyyy") -> Jan-2023 | Q8: =IFERROR(O8/N8,"") -> 0.16296874 | R8: =IF(OR(N8>$U$3,N8<$U$2),"Sales Outlier",IF(OR(O8>$U$6,O8<$U$4),"Profit Outlier",""))
A9: ORD-100163 | B9: 44933 | C9: 45114 | D9: Hassan Garcia | E9: Home Office | F9: North | G9: Lucknow | H9: Home & Kitchen | I9: Toaster | J9: Second Class | K9: 2 | L9: 1109.62 | M9: 0 | N9: 1109.62 | O9: 329.14 | P9: =TEXT(B9,"mmm-yyyy") -> Jan-2023 | Q9: =IFERROR(O9/N9,"") -> 0.29662407 | R9: =IF(OR(N9>$U$3,N9<$U$2),"Sales Outlier",IF(OR(O9>$U$6,O9<$U$4),"Profit Outlier",""))
A10: ORD-100053 | B10: 44934 | C10: 44938 | D10: Emma Garcia | E10: Home Office | F10: East | G10: Kolkata | H10: Furniture | I10: Bookshelf | J10: Same Day | K10: 3 | L10: 350.89 | M10: 0 | N10: 1052.67 | O10: 82.83 | P10: =TEXT(B10,"mmm-yyyy") -> Jan-2023 | Q10: =IFERROR(O10/N10,"") -> 0.078685628 | R10: =IF(OR(N10>$U$3,N10<$U$2),"Sales Outlier",IF(OR(O10>$U$6,O10<$U$4),"Profit Outlier",""))
A11: ORD-100367 | B11: 44934 | C11: 44940 | D11: Priya Khan | E11: Unknown | F11: South | G11: Hyderabad | H11: Clothing | I11: Sneakers | J11: First Class | K11: 1 | L11: 16.36 | M11: 0.1 | N11: 14.72 | O11: 1.97 | P11: =TEXT(B11,"mmm-yyyy") -> Jan-2023 | Q11: =IFERROR(O11/N11,"") -> 0.13383152 | R11: =IF(OR(N11>$U$3,N11<$U$2),"Sales Outlier",IF(OR(O11>$U$6,O11<$U$4),"Profit Outlier",""))
A12: ORD-100385 | B12: 44937 | C12: 44941 | D12: Ivan Garcia | E12: Consumer | F12: North | G12: Chandigarh | H12: Electronics | I12: Bluetooth Speaker | J12: Same Day | K12: 3 | L12: 667.22 | M12: 0.15 | N12: 1701.41 | O12: 212.43 | P12: =TEXT(B12,"mmm-yyyy") -> Jan-2023 | Q12: =IFERROR(O12/N12,"") -> 0.12485527 | R12: =IF(OR(N12>$U$3,N12<$U$2),"Sales Outlier",IF(OR(O12>$U$6,O12<$U$4),"Profit Outlier",""))
A13: ORD-100009 | B13: 44942 | C13: 44943 | D13: Tom Rossi | E13: Corporate | F13: South | G13: Bengaluru | H13: Electronics | I13: Tablet | J13: Second Class | K13: 1 | L13: 65.45 | M13: 0.2 | N13: 52.36 | O13: -128.24 | P13: =TEXT(B13,"mmm-yyyy") -> Jan-2023 | Q13: =IFERROR(O13/N13,"") -> -2.4491979 | R13: =IF(OR(N13>$U$3,N13<$U$2),"Sales Outlier",IF(OR(O13>$U$6,O13<$U$4),"Profit Outlier",""))
A14: ORD-100543 | B14: 44944 | C14: 44946 | D14: Mei Martin | E14: Consumer | F14: West | G14: Ahmedabad | H14: Home & Kitchen | I14: Cookware Set | J14: Same Day | K14: 2 | L14: 1008.82 | M14: 0.05 | N14: 1916.76 | O14: 121.13 | P14: =TEXT(B14,"mmm-yyyy") -> Jan-2023 | Q14: =IFERROR(O14/N14,"") -> 0.063195184 | R14: =IF(OR(N14>$U$3,N14<$U$2),"Sales Outlier",IF(OR(O14>$U$6,O14<$U$4),"Profit Outlier",""))
A15: ORD-100458 | B15: 44945 | C15: 44950 | D15: Diego Fernandez | E15: Unknown | F15: North | G15: Lucknow | H15: Furniture | I15: Dining Table | J15: Second Class | K15: 5 | L15: 819.92 | M15: 0 | N15: 4099.6 | O15: -155.8 | P15: =TEXT(B15,"mmm-yyyy") -> Jan-2023 | Q15: =IFERROR(O15/N15,"") -> -0.038003708 | R15: =IF(OR(N15>$U$3,N15<$U$2),"Sales Outlier",IF(OR(O15>$U$6,O15<$U$4),"Profit Outlier",""))
A16: ORD-100324 | B16: 44946 | C16: 44947 | D16: Nina Johnson | E16: Corporate | F16: North | G16: Delhi | H16: Home & Kitchen | I16: Air Fryer | J16: Standard Class | K16: 2 | L16: 901.92 | M16: 0.2 | N16: 1443.07 | O16: 394.48 | P16: =TEXT(B16,"mmm-yyyy") -> Jan-2023 | Q16: =IFERROR(O16/N16,"") -> 0.27336165 | R16: =IF(OR(N16>$U$3,N16<$U$2),"Sales Outlier",IF(OR(O16>$U$6,O16<$U$4),"Profit Outlier",""))
A17: ORD-100570 | B17: 44948 | C17: 44952 | D17: Carlos Sharma | E17: Corporate | F17: East | G17: Bhubaneswar | H17: Furniture | I17: Sofa | J17: Same Day | K17: 3 | L17: 1058.92 | M17: 0.1 | N17: 2859.08 | O17: -125.05 | P17: =TEXT(B17,"mmm-yyyy") -> Jan-2023 | Q17: =IFERROR(O17/N17,"") -> -0.043737846 | R17: =IF(OR(N17>$U$3,N17<$U$2),"Sales Outlier",IF(OR(O17>$U$6,O17<$U$4),"Profit Outlier",""))
A18: ORD-100089 | B18: 44950 | C18: 44953 | D18: Hassan Novak | E18: Corporate | F18: West | G18: Mumbai | H18: Home & Kitchen | I18: Cookware Set | J18: Second Class | K18: 2 | L18: 1002.61 | M18: 0 | N18: 2005.22 | O18: 215.12 | P18: =TEXT(B18,"mmm-yyyy") -> Jan-2023 | Q18: =IFERROR(O18/N18,"") -> 0.10728 | R18: =IF(OR(N18>$U$3,N18<$U$2),"Sales Outlier",IF(OR(O18>$U$6,O18<$U$4),"Profit Outlier",""))
... A35: ORD-100304 | B35: 44964 | C35: 45023 | D35: Tom Fernandez | E35: Corporate | F35: North | G35: Chandigarh | H35: Electronics | I35: Smartwatch | J35: First Class | K35: 5 | L35: 115.6 | M35: 0.1 | N35: 520.2 | O35: 130.45 | P35: =TEXT(B35,"mmm-yyyy") -> Feb-2023 | Q35: =IFERROR(O35/N35,"") -> 0.25076894 | R35: =IF(OR(N35>$U$3,N35<$U$2),"Sales Outlier",IF(OR(O35>$U$6,O35<$U$4),"Profit Outlier",""))
A36: ORD-100598 | B36: 44965 | D36: Kenji Petrov | E36: Consumer | F36: South | G36: Hyderabad | H36: Furniture | I36: Office Chair | J36: Second Class | K36: 5 | L36: 815.23 | M36: 0 | N36: 4076.15 | O36: -292.04 | P36: =TEXT(B36,"mmm-yyyy") -> Feb-2023 | Q36: =IFERROR(O36/N36,"") -> -0.071646039 | R36: =IF(OR(N36>$U$3,N36<$U$2),"Sales Outlier",IF(OR(O36>$U$6,O36<$U$4),"Profit Outlier",""))
A37: ORD-100464 | B37: 44966 | C37: 44971 | D37: Liam Kim | E37: Consumer | F37: North | G37: Delhi | H37: Furniture | I37: Dining Table | J37: First Class | K37: 3 | L37: 408.35 | M37: 0.15 | N37: 1041.29 | O37: 39.68 | P37: =TEXT(B37,"mmm-yyyy") -> Feb-2023 | Q37: =IFERROR(O37/N37,"") -> 0.038106579 | R37: =IF(OR(N37>$U$3,N37<$U$2),"Sales Outlier",IF(OR(O37>$U$6,O37<$U$4),"Profit Outlier",""))
A38: ORD-100533 | B38: 44967 | C38: 44974 | D38: Mei Chen | E38: Corporate | F38: South | G38: Hyderabad | H38: Office Supplies | I38: Stapler | J38: Same Day | K38: 1 | L38: 36.34 | M38: 0.2 | N38: 29.07 | O38: -0.18 | P38: =TEXT(B38,"mmm-yyyy") -> Feb-2023 | Q38: =IFERROR(O38/N38,"") -> -0.0061919505 | R38: =IF(OR(N38>$U$3,N38<$U$2),"Sales Outlier",IF(OR(O38>$U$6,O38<$U$4),"Profit Outlier",""))
A39: ORD-100014 | B39: 44967 | C39: 44970 | D39: Sofia Khan | E39: Unknown | F39: South | G39: Hyderabad | H39: Clothing | I39: Jeans | J39: First Class | K39: 1 | L39: 373.37 | M39: 0 | N39: 373.37 | O39: 88.59 | P39: =TEXT(B39,"mmm-yyyy") -> Feb-2023 | Q39: =IFERROR(O39/N39,"") -> 0.23727134 | R39: =IF(OR(N39>$U$3,N39<$U$2),"Sales Outlier",IF(OR(O39>$U$6,O39<$U$4),"Profit Outlier",""))
A40: ORD-100222 | B40: 44967 | C40: 44972 | D40: Maria Sharma | E40: Home Office | F40: West | G40: Pune | H40: Clothing | I40: T-Shirt | J40: Standard Class | K40: 2 | L40: 624.85 | M40: 0.15 | N40: 1062.25 | O40: 114.3 | P40: =TEXT(B40,"mmm-yyyy") -> Feb-2023 | Q40: =IFERROR(O40/N40,"") -> 0.10760179 | R40: =IF(OR(N40>$U$3,N40<$U$2),"Sales Outlier",IF(OR(O40>$U$6,O40<$U$4),"Profit Outlier",""))
A41: ORD-100212 | B41: 44969 | C41: 44972 | D41: Carlos Brown | E41: Consumer | F41: South | G41: Hyderabad | H41: Home & Kitchen | I41: Blender | J41: Second Class | K41: 5 | L41: 69.68 | M41: 0.2 | N41: 278.72 | O41: 63.89 | P41: =TEXT(B41,"mmm-yyyy") -> Feb-2023 | Q41: =IFERROR(O41/N41,"") -> 0.22922646 | R41: =IF(OR(N41>$U$3,N41<$U$2),"Sales Outlier",IF(OR(O41>$U$6,O41<$U$4),"Profit Outlier",""))
A42: ORD-100253 | B42: 44970 | C42: 44974 | D42: Ethan Martin | E42: Corporate | F42: West | G42: Ahmedabad | H42: Electronics | I42: Headphones | J42: Second Class | K42: 4 | L42: 71.99 | M42: 0 | N42: 287.96 | O42: 46.28 | P42: =TEXT(B42,"mmm-yyyy") -> Feb-2023 | Q42: =IFERROR(O42/N42,"") -> 0.16071677 | R42: =IF(OR(N42>$U$3,N42<$U$2),"Sales Outlier",IF(OR(O42>$U$6,O42<$U$4),"Profit Outlier",""))
A43: ORD-100625 | B43: 44970 | C43: 44971 | D43: Carlos Smith | E43: Unknown | F43: West | G43: Ahmedabad | H43: Furniture | I43: Office Chair | J43: Same Day | K43: 2 | L43: 198.69 | M43: 0.2 | N43: 317.9 | O43: 76.11 | P43: =TEXT(B43,"mmm-yyyy") -> Feb-2023 | Q43: =IFERROR(O43/N43,"") -> 0.23941491 | R43: =IF(OR(N43>$U$3,N43<$U$2),"Sales Outlier",IF(OR(O43>$U$6,O43<$U$4),"Profit Outlier",""))
A44: ORD-100337 | B44: 44972 | C44: 44973 | D44: Omar Petrov | E44: Home Office | F44: West | G44: Pune | H44: Home & Kitchen | I44: Toaster | J44: Standard Class | K44: 2 | L44: 295.57 | M44: 0 | N44: 591.14 | O44: 96.15 | P44: =TEXT(B44,"mmm-yyyy") -> Feb-2023 | Q44: =IFERROR(O44/N44,"") -> 0.16265183 | R44: =IF(OR(N44>$U$3,N44<$U$2),"Sales Outlier",IF(OR(O44>$U$6,O44<$U$4),"Profit Outlier",""))
A45: ORD-100066 | B45: 44975 | C45: 44982 | D45: Liam Khan | E45: Unknown | F45: West | G45: Ahmedabad | H45: Office Supplies | I45: Notebook | J45: Same Day | K45: 2 | L45: 346.9 | M45: 0 | N45: 693.8 | O45: 67.91 | P45: =TEXT(B45,"mmm-yyyy") -> Feb-2023 | Q45: =IFERROR(O45/N45,"") -> 0.097881234 | R45: =IF(OR(N45>$U$3,N45<$U$2),"Sales Outlier",IF(OR(O45>$U$6,O45<$U$4),"Profit Outlier",""))
A46: ORD-100274 | B46: 44976 | C46: 44979 | D46: Arjun Chen | E46: Corporate | F46: North | G46: Delhi | H46: Office Supplies | I46: Printer Paper | J46: First Class | K46: 5 | L46: 765.32 | M46: 0.1 | N46: 3443.94 | O46: 583.55 | P46: =TEXT(B46,"mmm-yyyy") -> Feb-2023 | Q46: =IFERROR(O46/N46,"") -> 0.16944256 | R46: =IF(OR(N46>$U$3,N46<$U$2),"Sales Outlier",IF(OR(O46>$U$6,O46<$U$4),"Profit Outlier",""))
A47: ORD-100562 | B47: 44976 | C47: 44981 | D47: Unknown Customer | E47: Home Office | F47: East | G47: Bhubaneswar | H47: Home & Kitchen | I47: Air Fryer | J47: Standard Class | K47: 2 | L47: 770.91 | M47: 0 | N47: 1541.82 | O47: -23.58 | P47: =TEXT(B47,"mmm-yyyy") -> Feb-2023 | Q47: =IFERROR(O47/N47,"") -> -0.015293614 | R47: =IF(OR(N47>$U$3,N47<$U$2),"Sales Outlier",IF(OR(O47>$U$6,O47<$U$4),"Profit Outlier",""))
A48: ORD-100154 | B48: 44976 | C48: 44982 | D48: Kenji Fernandez | E48: Corporate | F48: North | G48: Delhi | H48: Home & Kitchen | I48: Blender | J48: Standard Class | K48: 1 | L48: 786.01 | M48: 0 | N48: 786.01 | O48: 167.29 | P48: =TEXT(B48,"mmm-yyyy") -> Feb-2023 | Q48: =IFERROR(O48/N48,"") -> 0.21283444 | R48: =IF(OR(N48>$U$3,N48<$U$2),"Sales Outlier",IF(OR(O48>$U$6,O48<$U$4),"Profit Outlier",""))
... A145: ORD-100643 | B145: 45108 | C145: 45113 | D145: John Petrov | E145: Unknown | F145: East | G145: Kolkata | H145: Electronics | I145: Smartphone | J145: Second Class | K145: 5 | L145: 675.1 | M145: 0.1 | N145: 3037.95 | O145: -167.83 | P145: =TEXT(B145,"mmm-yyyy") -> Jul-2023 | Q145: =IFERROR(O145/N145,"") -> -0.055244491 | R145: =IF(OR(N145>$U$3,N145<$U$2),"Sales Outlier",IF(OR(O145>$U$6,O145<$U$4),"Profit Outlier",""))
A146: ORD-100557 | B146: 45108 | D146: Liam Okafor | E146: Corporate | F146: West | G146: Mumbai | H146: Furniture | I146: Desk | J146: First Class | K146: 2 | L146: 119.56 | M146: 0.1 | N146: 215.21 | O146: 12.49 | P146: =TEXT(B146,"mmm-yyyy") -> Jul-2023 | Q146: =IFERROR(O146/N146,"") -> 0.058036337 | R146: =IF(OR(N146>$U$3,N146<$U$2),"Sales Outlier",IF(OR(O146>$U$6,O146<$U$4),"Profit Outlier",""))
A147: ORD-100151 | B147: 45111 | C147: 45118 | D147: Noah Johnson | E147: Unknown | F147: East | G147: Bhubaneswar | H147: Clothing | I147: Cap | J147: Same Day | K147: 2 | L147: 176.15 | M147: 0 | N147: 176.15 | O147: -1.02 | P147: =TEXT(B147,"mmm-yyyy") -> Jul-2023 | Q147: =IFERROR(O147/N147,"") -> -0.0057905194 | R147: =IF(OR(N147>$U$3,N147<$U$2),"Sales Outlier",IF(OR(O147>$U$6,O147<$U$4),"Profit Outlier",""))
A148: ORD-100478 | B148: 45111 | C148: 45114 | D148: Zara Ali | E148: Unknown | F148: West | G148: Ahmedabad | H148: Home & Kitchen | I148: Cookware Set | J148: Second Class | K148: 4 | L148: 583.66 | M148: 0 | N148: 2334.64 | O148: 141.73 | P148: =TEXT(B148,"mmm-yyyy") -> Jul-2023 | Q148: =IFERROR(O148/N148,"") -> 0.060707432 | R148: =IF(OR(N148>$U$3,N148<$U$2),"Sales Outlier",IF(OR(O148>$U$6,O148<$U$4),"Profit Outlier",""))
A149: ORD-100579 | B149: 45113 | C149: 45266 | D149: Maria Chen | E149: Consumer | F149: South | G149: Hyderabad | H149: Electronics | I149: Smartphone | J149: Standard Class | K149: 1 | L149: 216.64 | M149: 0 | N149: 216.64 | O149: 57.01 | P149: =TEXT(B149,"mmm-yyyy") -> Jul-2023 | Q149: =IFERROR(O149/N149,"") -> 0.26315547 | R149: =IF(OR(N149>$U$3,N149<$U$2),"Sales Outlier",IF(OR(O149>$U$6,O149<$U$4),"Profit Outlier",""))
A150: ORD-100190 | B150: 45114 | C150: 45120 | D150: Ivan Patel | E150: Corporate | F150: West | G150: Pune | H150: Office Supplies | I150: Printer Paper | J150: Standard Class | K150: 2 | L150: 1073.71 | M150: 0.1 | N150: 1932.68 | O150: -13.43 | P150: =TEXT(B150,"mmm-yyyy") -> Jul-2023 | Q150: =IFERROR(O150/N150,"") -> -0.0069489 | R150: =IF(OR(N150>$U$3,N150<$U$2),"Sales Outlier",IF(OR(O150>$U$6,O150<$U$4),"Profit Outlier",""))
A151: ORD-100351 | B151: 45114 | C151: 45120 | D151: Diego Sharma | E151: Home Office | F151: South | G151: Hyderabad | H151: Home & Kitchen | I151: Toaster | J151: Standard Class | K151: 2 | L151: 464.67 | M151: 0 | N151: 464.67 | O151: 65.97 | P151: =TEXT(B151,"mmm-yyyy") -> Jul-2023 | Q151: =IFERROR(O151/N151,"") -> 0.14197172 | R151: =IF(OR(N151>$U$3,N151<$U$2),"Sales Outlier",IF(OR(O151>$U$6,O151<$U$4),"Profit Outlier",""))
A152: ORD-100069 | B152: 45117 | C152: 45121 | D152: Ivan Novak | E152: Unknown | F152: West | G152: Mumbai | H152: Office Supplies | I152: Printer Paper | J152: First Class | K152: 2 | L152: 1152.82 | M152: 0 | N152: 2305.64 | O152: 803.2 | P152: =TEXT(B152,"mmm-yyyy") -> Jul-2023 | Q152: =IFERROR(O152/N152,"") -> 0.34836314 | R152: =IF(OR(N152>$U$3,N152<$U$2),"Sales Outlier",IF(OR(O152>$U$6,O152<$U$4),"Profit Outlier",""))
A153: ORD-100064 | B153: 45118 | C153: 45124 | D153: Lucas Wang | E153: Consumer | F153: West | G153: Pune | H153: Electronics | I153: Smartwatch | J153: Standard Class | K153: 4 | L153: 292.47 | M153: 0.15 | N153: 994.4 | O153: 291.36 | P153: =TEXT(B153,"mmm-yyyy") -> Jul-2023 | Q153: =IFERROR(O153/N153,"") -> 0.2930008 | R153: =IF(OR(N153>$U$3,N153<$U$2),"Sales Outlier",IF(OR(O153>$U$6,O153<$U$4),"Profit Outlier",""))
A154: ORD-100231 | B154: 45118 | C154: 45123 | D154: Ethan Ali | E154: Consumer | F154: East | G154: Bhubaneswar | H154: Clothing | I154: Cap | J154: First Class | K154: 2 | L154: 687.32 | M154: 0.15 | N154: 1168.44 | O154: 100.77 | P154: =TEXT(B154,"mmm-yyyy") -> Jul-2023 | Q154: =IFERROR(O154/N154,"") -> 0.086243196 | R154: =IF(OR(N154>$U$3,N154<$U$2),"Sales Outlier",IF(OR(O154>$U$6,O154<$U$4),"Profit Outlier",""))
A155: ORD-100499 | B155: 45118 | C155: 45121 | D155: Kenji Novak | E155: Unknown | F155: South | G155: Hyderabad | H155: Clothing | I155: Sneakers | J155: First Class | K155: 4 | L155: 407.32 | M155: 0 | N155: 1629.28 | O155: 259.36 | P155: =TEXT(B155,"mmm-yyyy") -> Jul-2023 | Q155: =IFERROR(O155/N155,"") -> 0.15918688 | R155: =IF(OR(N155>$U$3,N155<$U$2),"Sales Outlier",IF(OR(O155>$U$6,O155<$U$4),"Profit Outlier",""))
A156: ORD-100280 | B156: 45120 | C156: 45127 | D156: Anaya Okafor | E156: Consumer | F156: South | G156: Hyderabad | H156: Home & Kitchen | I156: Toaster | J156: Standard Class | K156: 3 | L156: 1182.03 | M156: 0.15 | N156: 3014.18 | O156: 365.44 | P156: =TEXT(B156,"mmm-yyyy") -> Jul-2023 | Q156: =IFERROR(O156/N156,"") -> 0.12124027 | R156: =IF(OR(N156>$U$3,N156<$U$2),"Sales Outlier",IF(OR(O156>$U$6,O156<$U$4),"Profit Outlier",""))
A157: ORD-100252 | B157: 45122 | C157: 45125 | D157: Zara Khan | E157: Consumer | F157: East | G157: Patna | H157: Furniture | I157: Bookshelf | J157: Same Day | K157: 1 | L157: 1161.18 | M157: 0 | N157: 1161.18 | O157: 134.57 | P157: =TEXT(B157,"mmm-yyyy") -> Jul-2023 | Q157: =IFERROR(O157/N157,"") -> 0.11589073 | R157: =IF(OR(N157>$U$3,N157<$U$2),"Sales Outlier",IF(OR(O157>$U$6,O157<$U$4),"Profit Outlier",""))
A158: ORD-100394 | B158: 45122 | C158: 45124 | D158: Ivan Khan | E158: Home Office | F158: South | G158: Bengaluru | H158: Home & Kitchen | I158: Blender | J158: First Class | K158: 1 | L158: 705.94 | M158: 0 | N158: 705.94 | O158: 159.83 | P158: =TEXT(B158,"mmm-yyyy") -> Jul-2023 | Q158: =IFERROR(O158/N158,"") -> 0.22640734 | R158: =IF(OR(N158>$U$3,N158<$U$2),"Sales Outlier",IF(OR(O158>$U$6,O158<$U$4),"Profit Outlier",""))
... A180: ORD-100279 | B180: 45146 | C180: 45151 | D180: Fatima Brown | E180: Corporate | F180: West | G180: Pune | H180: Electronics | I180: Smartphone | J180: Same Day | K180: 4 | L180: 1177.65 | M180: 0.15 | N180: 4004.01 | O180: 973.07 | P180: =TEXT(B180,"mmm-yyyy") -> Aug-2023 | Q180: =IFERROR(O180/N180,"") -> 0.24302387 | R180: =IF(OR(N180>$U$3,N180<$U$2),"Sales Outlier",IF(OR(O180>$U$6,O180<$U$4),"Profit Outlier",""))
A181: ORD-100491 | B181: 45146 | D181: Anaya Kim | E181: Unknown | F181: West | G181: Pune | H181: Office Supplies | I181: Printer Paper | J181: First Class | K181: 4 | L181: 639.17 | M181: 0.2 | N181: 2045.34 | O181: 435.24 | P181: =TEXT(B181,"mmm-yyyy") -> Aug-2023 | Q181: =IFERROR(O181/N181,"") -> 0.21279592 | R181: =IF(OR(N181>$U$3,N181<$U$2),"Sales Outlier",IF(OR(O181>$U$6,O181<$U$4),"Profit Outlier",""))
A182: ORD-100149 | B182: 45154 | C182: 45160 | D182: Ethan Okafor | E182: Home Office | F182: West | G182: Mumbai | H182: Clothing | I182: T-Shirt | J182: Standard Class | K182: 2 | L182: 415.08 | M182: 0 | N182: 830.16 | O182: 231.02 | P182: =TEXT(B182,"mmm-yyyy") -> Aug-2023 | Q182: =IFERROR(O182/N182,"") -> 0.2782837 | R182: =IF(OR(N182>$U$3,N182<$U$2),"Sales Outlier",IF(OR(O182>$U$6,O182<$U$4),"Profit Outlier",""))
A183: ORD-100565 | B183: 45155 | C183: 45156 | D183: Fatima Johnson | E183: Corporate | F183: North | G183: Lucknow | H183: Clothing | I183: T-Shirt | J183: First Class | K183: 2 | L183: 159.02 | M183: 0 | N183: 159.02 | O183: 7.52 | P183: =TEXT(B183,"mmm-yyyy") -> Aug-2023 | Q183: =IFERROR(O183/N183,"") -> 0.047289649 | R183: =IF(OR(N183>$U$3,N183<$U$2),"Sales Outlier",IF(OR(O183>$U$6,O183<$U$4),"Profit Outlier",""))
A184: ORD-100474 | B184: 45156 | C184: 45158 | D184: Ivan Kim | E184: Corporate | F184: East | G184: Patna | H184: Furniture | I184: Office Chair | J184: Standard Class | K184: 3 | L184: 332.25 | M184: 0.15 | N184: 847.24 | O184: 21.51 | P184: =TEXT(B184,"mmm-yyyy") -> Aug-2023 | Q184: =IFERROR(O184/N184,"") -> 0.02538832 | R184: =IF(OR(N184>$U$3,N184<$U$2),"Sales Outlier",IF(OR(O184>$U$6,O184<$U$4),"Profit Outlier",""))
A185: ORD-100374 | B185: 45157 | C185: 45163 | D185: Ivan Johnson | E185: Home Office | F185: West | G185: Ahmedabad | H185: Electronics | I185: Laptop | J185: Standard Class | K185: 2 | L185: 994.32 | M185: 0.05 | N185: 1889.21 | O185: 586.73 | P185: =TEXT(B185,"mmm-yyyy") -> Aug-2023 | Q185: =IFERROR(O185/N185,"") -> 0.31056897 | R185: =IF(OR(N185>$U$3,N185<$U$2),"Sales Outlier",IF(OR(O185>$U$6,O185<$U$4),"Profit Outlier",""))
A186: ORD-100111 | B186: 45157 | C186: 45162 | D186: Maria Tanaka | E186: Unknown | F186: North | G186: Lucknow | H186: Home & Kitchen | I186: Blender | J186: Second Class | K186: 2 | L186: 354.05 | M186: 0.1 | N186: 637.29 | O186: 82.76 | P186: =TEXT(B186,"mmm-yyyy") -> Aug-2023 | Q186: =IFERROR(O186/N186,"") -> 0.12986239 | R186: =IF(OR(N186>$U$3,N186<$U$2),"Sales Outlier",IF(OR(O186>$U$6,O186<$U$4),"Profit Outlier",""))
A187: ORD-100039 | B187: 45159 | C187: 45165 | D187: Fatima Khan | E187: Consumer | F187: North | G187: Delhi | H187: Home & Kitchen | I187: Blender | J187: Second Class | K187: 2 | L187: 759.24 | M187: 0.1 | N187: 1366.63 | O187: 62.82 | P187: =TEXT(B187,"mmm-yyyy") -> Aug-2023 | Q187: =IFERROR(O187/N187,"") -> 0.045967087 | R187: =IF(OR(N187>$U$3,N187<$U$2),"Sales Outlier",IF(OR(O187>$U$6,O187<$U$4),"Profit Outlier",""))
A188: ORD-100156 | B188: 45163 | D188: Aisha Kim | E188: Corporate | F188: North | G188: Delhi | H188: Home & Kitchen | I188: Blender | J188: First Class | K188: 1 | L188: 1086.21 | M188: 0 | N188: 1086.21 | O188: 307.95 | P188: =TEXT(B188,"mmm-yyyy") -> Aug-2023 | Q188: =IFERROR(O188/N188,"") -> 0.28350871 | R188: =IF(OR(N188>$U$3,N188<$U$2),"Sales Outlier",IF(OR(O188>$U$6,O188<$U$4),"Profit Outlier",""))
A189: ORD-100220 | B189: 45163 | C189: 45168 | D189: Isabella Smith | E189: Unknown | F189: North | G189: Delhi | H189: Home & Kitchen | I189: Air Fryer | J189: Second Class | K189: 3 | L189: 728.7 | M189: 0.2 | N189: 1748.88 | O189: 220.44 | P189: =TEXT(B189,"mmm-yyyy") -> Aug-2023 | Q189: =IFERROR(O189/N189,"") -> 0.12604638 | R189: =IF(OR(N189>$U$3,N189<$U$2),"Sales Outlier",IF(OR(O189>$U$6,O189<$U$4),"Profit Outlier",""))
A190: ORD-100411 | B190: 45164 | C190: 45166 | D190: Arjun Garcia | E190: Home Office | F190: South | G190: Bengaluru | H190: Furniture | I190: Sofa | J190: Same Day | K190: 1 | L190: 1062.82 | M190: 0 | N190: 1062.82 | O190: 269.33 | P190: =TEXT(B190,"mmm-yyyy") -> Aug-2023 | Q190: =IFERROR(O190/N190,"") -> 0.25341074 | R190: =IF(OR(N190>$U$3,N190<$U$2),"Sales Outlier",IF(OR(O190>$U$6,O190<$U$4),"Profit Outlier",""))
A191: ORD-100193 | B191: 45168 | C191: 45173 | D191: Diego Patel | E191: Corporate | F191: South | G191: Bengaluru | H191: Home & Kitchen | I191: Cookware Set | J191: First Class | K191: 1 | L191: 866.37 | M191: 0 | N191: 866.37 | O191: 227.47 | P191: =TEXT(B191,"mmm-yyyy") -> Aug-2023 | Q191: =IFERROR(O191/N191,"") -> 0.26255526 | R191: =IF(OR(N191>$U$3,N191<$U$2),"Sales Outlier",IF(OR(O191>$U$6,O191<$U$4),"Profit Outlier",""))
A192: ORD-100225 | B192: 45170 | C192: 45172 | D192: Amara Tanaka | E192: Consumer | F192: West | G192: Mumbai | H192: Clothing | I192: Sneakers | J192: Second Class | K192: 1 | L192: 731.54 | M192: 0.15 | N192: 621.81 | O192: 184.66 | P192: =TEXT(B192,"mmm-yyyy") -> Sep-2023 | Q192: =IFERROR(O192/N192,"") -> 0.29697174 | R192: =IF(OR(N192>$U$3,N192<$U$2),"Sales Outlier",IF(OR(O192>$U$6,O192<$U$4),"Profit Outlier",""))
A193: ORD-100637 | B193: 45173 | C193: 45177 | D193: Carlos Sharma | E193: Consumer | F193: West | G193: Mumbai | H193: Clothing | I193: Jeans | J193: Same Day | K193: 3 | L193: 801.18 | M193: 0.05 | N193: 2283.36 | O193: -117.7 | P193: =TEXT(B193,"mmm-yyyy") -> Sep-2023 | Q193: =IFERROR(O193/N193,"") -> -0.051546843 | R193: =IF(OR(N193>$U$3,N193<$U$2),"Sales Outlier",IF(OR(O193>$U$6,O193<$U$4),"Profit Outlier",""))
A194: ORD-100449 | B194: 45173 | C194: 45175 | D194: Yuki Novak | E194: Home Office | F194: South | G194: Hyderabad | H194: Electronics | I194: Smartphone | J194: Standard Class | K194: 2 | L194: 983.17 | M194: 0 | N194: 1966.34 | O194: -108.13 | P194: =TEXT(B194,"mmm-yyyy") -> Sep-2023 | Q194: =IFERROR(O194/N194,"") -> -0.05499049 | R194: =IF(OR(N194>$U$3,N194<$U$2),"Sales Outlier",IF(OR(O194>$U$6,O194<$U$4),"Profit Outlier",""))
A195: ORD-100434 | B195: 45175 | C195: 45181 | D195: Tom Patel | E195: Unknown | F195: North | G195: Delhi | H195: Office Supplies | I195: Printer Paper | J195: Same Day | K195: 1 | L195: 426.85 | M195: 0 | N195: 426.85 | O195: -1.87 | P195: =TEXT(B195,"mmm-yyyy") -> Sep-2023 | Q195: =IFERROR(O195/N195,"") -> -0.0043809301 | R195: =IF(OR(N195>$U$3,N195<$U$2),"Sales Outlier",IF(OR(O195>$U$6,O195<$U$4),"Profit Outlier",""))
A196: ORD-100102 | B196: 45175 | C196: 45180 | D196: Isabella Fernandez | E196: Home Office | F196: East | G196: Bhubaneswar | H196: Clothing | I196: Sneakers | J196: Second Class | K196: 1 | L196: 871.19 | M196: 0.2 | N196: 696.95 | O196: -23.93 | P196: =TEXT(B196,"mmm-yyyy") -> Sep-2023 | Q196: =IFERROR(O196/N196,"") -> -0.034335318 | R196: =IF(OR(N196>$U$3,N196<$U$2),"Sales Outlier",IF(OR(O196>$U$6,O196<$U$4),"Profit Outlier",""))
A197: ORD-100522 | B197: 45176 | C197: 45181 | D197: Amara Tanaka | E197: Consumer | F197: South | G197: Bengaluru | H197: Electronics | I197: Smartphone | J197: First Class | K197: 3 | L197: 77.73 | M197: 0.05 | N197: 221.53 | O197: 56.6 | P197: =TEXT(B197,"mmm-yyyy") -> Sep-2023 | Q197: =IFERROR(O197/N197,"") -> 0.25549587 | R197: =IF(OR(N197>$U$3,N197<$U$2),"Sales Outlier",IF(OR(O197>$U$6,O197<$U$4),"Profit Outlier",""))
A198: ORD-100621 | B198: 45176 | C198: 45182 | D198: Kenji Smith | E198: Unknown | F198: West | G198: Mumbai | H198: Home & Kitchen | I198: Toaster | J198: Second Class | K198: 1 | L198: 825.36 | M198: 0.2 | N198: 660.29 | O198: 79.85 | P198: =TEXT(B198,"mmm-yyyy") -> Sep-2023 | Q198: =IFERROR(O198/N198,"") -> 0.12093171 | R198: =IF(OR(N198>$U$3,N198<$U$2),"Sales Outlier",IF(OR(O198>$U$6,O198<$U$4),"Profit Outlier",""))
A199: ORD-100469 | B199: 45176 | C199: 45179 | D199: Maria Wang | E199: Consumer | F199: West | G199: Ahmedabad | H199: Office Supplies | I199: Printer Paper | J199: Second Class | K199: 2 | L199: 1004.03 | M199: 0.1 | N199: 1807.25 | O199: 15.31 | P199: =TEXT(B199,"mmm-yyyy") -> Sep-2023 | Q199: =IFERROR(O199/N199,"") -> 0.0084714345 | R199: =IF(OR(N199>$U$3,N199<$U$2),"Sales Outlier",IF(OR(O199>$U$6,O199<$U$4),"Profit Outlier",""))
A200: ORD-100095 | B200: 45178 | C200: 45182 | D200: Isabella Brown | E200: Unknown | F200: South | G200: Bengaluru | H200: Furniture | I200: Desk | J200: Standard Class | K200: 2 | L200: 458.91 | M200: 0 | N200: 917.82 | O200: -22.3 | P200: =TEXT(B200,"mmm-yyyy") -> Sep-2023 | Q200: =IFERROR(O200/N200,"") -> -0.024296703 | R200: =IF(OR(N200>$U$3,N200<$U$2),"Sales Outlier",IF(OR(O200>$U$6,O200<$U$4),"Profit Outlier",""))
... A245: ORD-100416 | B245: 45232 | C245: 45239 | D245: Tom Petrov | E245: Home Office | F245: South | G245: Chennai | H245: Electronics | I245: Smartphone | J245: Same Day | K245: 1 | L245: 332.32 | M245: 0 | N245: 332.32 | O245: 90.97 | P245: =TEXT(B245,"mmm-yyyy") -> Nov-2023 | Q245: =IFERROR(O245/N245,"") -> 0.27374218 | R245: =IF(OR(N245>$U$3,N245<$U$2),"Sales Outlier",IF(OR(O245>$U$6,O245<$U$4),"Profit Outlier",""))
A246: ORD-100180 | B246: 45236 | D246: Anaya Khan | E246: Home Office | F246: South | G246: Hyderabad | H246: Electronics | I246: Smartwatch | J246: Second Class | K246: 3 | L246: 257.76 | M246: 0.05 | N246: 734.62 | O246: -35.99 | P246: =TEXT(B246,"mmm-yyyy") -> Nov-2023 | Q246: =IFERROR(O246/N246,"") -> -0.048991315 | R246: =IF(OR(N246>$U$3,N246<$U$2),"Sales Outlier",IF(OR(O246>$U$6,O246<$U$4),"Profit Outlier",""))
A247: ORD-100070 | B247: 45236 | C247: 45094 | D247: Yuki Johnson | E247: Consumer | F247: East | G247: Kolkata | H247: Electronics | I247: Smartwatch | J247: Standard Class | K247: 3 | L247: 1070.14 | M247: 0 | N247: 3210.42 | O247: 823.25 | P247: =TEXT(B247,"mmm-yyyy") -> Nov-2023 | Q247: =IFERROR(O247/N247,"") -> 0.25643062 | R247: =IF(OR(N247>$U$3,N247<$U$2),"Sales Outlier",IF(OR(O247>$U$6,O247<$U$4),"Profit Outlier",""))
A248: ORD-100272 | B248: 45236 | C248: 45243 | D248: Amara Novak | E248: Consumer | F248: West | G248: Mumbai | H248: Office Supplies | I248: Binder | J248: Standard Class | K248: 2 | L248: 55.47 | M248: 0 | N248: 55.47 | O248: 1.01 | P248: =TEXT(B248,"mmm-yyyy") -> Nov-2023 | Q248: =IFERROR(O248/N248,"") -> 0.01820804 | R248: =IF(OR(N248>$U$3,N248<$U$2),"Sales Outlier",IF(OR(O248>$U$6,O248<$U$4),"Profit Outlier",""))
A249: ORD-100110 | B249: 45237 | C249: 45121 | D249: Grace Sharma | E249: Unknown | F249: West | G249: Mumbai | H249: Home & Kitchen | I249: Cookware Set | J249: Second Class | K249: 2 | L249: 590.12 | M249: 0.05 | N249: 1121.23 | O249: -13.67 | P249: =TEXT(B249,"mmm-yyyy") -> Nov-2023 | Q249: =IFERROR(O249/N249,"") -> -0.012191968 | R249: =IF(OR(N249>$U$3,N249<$U$2),"Sales Outlier",IF(OR(O249>$U$6,O249<$U$4),"Profit Outlier",""))
A250: ORD-100217 | B250: 45239 | C250: 45242 | D250: Hassan Johnson | E250: Home Office | F250: South | G250: Hyderabad | H250: Home & Kitchen | I250: Toaster | J250: Second Class | K250: 1 | L250: 52.5 | M250: 0.2 | N250: 42 | O250: 1.51 | P250: =TEXT(B250,"mmm-yyyy") -> Nov-2023 | Q250: =IFERROR(O250/N250,"") -> 0.035952381 | R250: =IF(OR(N250>$U$3,N250<$U$2),"Sales Outlier",IF(OR(O250>$U$6,O250<$U$4),"Profit Outlier",""))
A251: ORD-100614 | B251: 45240 | C251: 45242 | D251: Lucas Petrov | E251: Corporate | F251: South | G251: Hyderabad | H251: Office Supplies | I251: Printer Paper | J251: Same Day | K251: 2 | L251: 681.39 | M251: 0.1 | N251: 1226.5 | O251: 368.87 | P251: =TEXT(B251,"mmm-yyyy") -> Nov-2023 | Q251: =IFERROR(O251/N251,"") -> 0.3007501 | R251: =IF(OR(N251>$U$3,N251<$U$2),"Sales Outlier",IF(OR(O251>$U$6,O251<$U$4),"Profit Outlier",""))
A252: ORD-100558 | B252: 45240 | C252: 45241 | D252: Omar Said | E252: Corporate | F252: North | G252: Delhi | H252: Furniture | I252: Office Chair | J252: Second Class | K252: 1 | L252: 10.57 | M252: 0.15 | N252: 8.98 | O252: 1.67 | P252: =TEXT(B252,"mmm-yyyy") -> Nov-2023 | Q252: =IFERROR(O252/N252,"") -> 0.18596882 | R252: =IF(OR(N252>$U$3,N252<$U$2),"Sales Outlier",IF(OR(O252>$U$6,O252<$U$4),"Profit Outlier",""))
A253: ORD-100496 | B253: 45242 | C253: 45249 | D253: Zara Patel | E253: Home Office | F253: South | G253: Chennai | H253: Office Supplies | I253: Pen Set | J253: First Class | K253: 1 | L253: 1053.25 | M253: 0.05 | N253: 1000.59 | O253: 70.73 | P253: =TEXT(B253,"mmm-yyyy") -> Nov-2023 | Q253: =IFERROR(O253/N253,"") -> 0.070688294 | R253: =IF(OR(N253>$U$3,N253<$U$2),"Sales Outlier",IF(OR(O253>$U$6,O253<$U$4),"Profit Outlier",""))
A254: ORD-100293 | B254: 45243 | C254: 45249 | D254: Mei Khan | E254: Unknown | F254: North | G254: Chandigarh | H254: Electronics | I254: Bluetooth Speaker | J254: First Class | K254: 2 | L254: 307.31 | M254: 0.15 | N254: 522.43 | O254: -50.39 | P254: =TEXT(B254,"mmm-yyyy") -> Nov-2023 | Q254: =IFERROR(O254/N254,"") -> -0.096453113 | R254: =IF(OR(N254>$U$3,N254<$U$2),"Sales Outlier",IF(OR(O254>$U$6,O254<$U$4),"Profit Outlier",""))
A255: ORD-100197 | B255: 45243 | C255: 45245 | D255: Aisha Tanaka | E255: Corporate | F255: North | G255: Delhi | H255: Office Supplies | I255: Binder | J255: Second Class | K255: 2 | L255: 105.75 | M255: 0.15 | N255: 179.78 | O255: -15.13 | P255: =TEXT(B255,"mmm-yyyy") -> Nov-2023 | Q255: =IFERROR(O255/N255,"") -> -0.084158416 | R255: =IF(OR(N255>$U$3,N255<$U$2),"Sales Outlier",IF(OR(O255>$U$6,O255<$U$4),"Profit Outlier",""))
A256: ORD-100360 | B256: 45245 | C256: 45247 | D256: Sofia Petrov | E256: Home Office | F256: South | G256: Hyderabad | H256: Furniture | I256: Dining Table | J256: Same Day | K256: 1 | L256: 514.36 | M256: 0.15 | N256: 437.21 | O256: 44.47 | P256: =TEXT(B256,"mmm-yyyy") -> Nov-2023 | Q256: =IFERROR(O256/N256,"") -> 0.10171314 | R256: =IF(OR(N256>$U$3,N256<$U$2),"Sales Outlier",IF(OR(O256>$U$6,O256<$U$4),"Profit Outlier",""))
A257: ORD-100050 | B257: 45246 | C257: 45249 | D257: Lucas Patel | E257: Consumer | F257: West | G257: Pune | H257: Office Supplies | I257: Pen Set | J257: Standard Class | K257: 1 | L257: 1162.24 | M257: 0.2 | N257: 929.79 | O257: 260.73 | P257: =TEXT(B257,"mmm-yyyy") -> Nov-2023 | Q257: =IFERROR(O257/N257,"") -> 0.28041816 | R257: =IF(OR(N257>$U$3,N257<$U$2),"Sales Outlier",IF(OR(O257>$U$6,O257<$U$4),"Profit Outlier",""))
A258: ORD-100483 | B258: 45246 | C258: 45253 | D258: Lucas Smith | E258: Consumer | F258: South | G258: Bengaluru | H258: Electronics | I258: Bluetooth Speaker | J258: Second Class | K258: 5 | L258: 237.17 | M258: 0.2 | N258: 948.68 | O258: 318.92 | P258: =TEXT(B258,"mmm-yyyy") -> Nov-2023 | Q258: =IFERROR(O258/N258,"") -> 0.33617237 | R258: =IF(OR(N258>$U$3,N258<$U$2),"Sales Outlier",IF(OR(O258>$U$6,O258<$U$4),"Profit Outlier",""))
... A296: ORD-100436 | B296: 45287 | C296: 45290 | D296: Nina Chen | E296: Unknown | F296: South | G296: Hyderabad | H296: Office Supplies | I296: Notebook | J296: First Class | K296: 2 | L296: 795.95 | M296: 0.15 | N296: 676.56 | O296: 63.52 | P296: =TEXT(B296,"mmm-yyyy") -> Dec-2023 | Q296: =IFERROR(O296/N296,"") -> 0.093886721 | R296: =IF(OR(N296>$U$3,N296<$U$2),"Sales Outlier",IF(OR(O296>$U$6,O296<$U$4),"Profit Outlier",""))
A297: ORD-100645 | B297: 45288 | D297: Raj Novak | E297: Consumer | F297: West | G297: Mumbai | H297: Home & Kitchen | I297: Vacuum Cleaner | J297: Standard Class | K297: 1 | L297: 430.73 | M297: 0 | N297: 430.73 | O297: -11.62 | P297: =TEXT(B297,"mmm-yyyy") -> Dec-2023 | Q297: =IFERROR(O297/N297,"") -> -0.026977457 | R297: =IF(OR(N297>$U$3,N297<$U$2),"Sales Outlier",IF(OR(O297>$U$6,O297<$U$4),"Profit Outlier",""))
A298: ORD-100526 | B298: 45289 | C298: 45413 | D298: Kenji Ali | E298: Unknown | F298: West | G298: Mumbai | H298: Office Supplies | I298: Printer Paper | J298: Second Class | K298: 2 | L298: 370.95 | M298: 0 | N298: 741.9 | O298: 180.28 | P298: =TEXT(B298,"mmm-yyyy") -> Dec-2023 | Q298: =IFERROR(O298/N298,"") -> 0.24299771 | R298: =IF(OR(N298>$U$3,N298<$U$2),"Sales Outlier",IF(OR(O298>$U$6,O298<$U$4),"Profit Outlier",""))
A299: ORD-100120 | B299: 45293 | C299: 45506 | D299: Olga Wang | E299: Unknown | F299: North | G299: Delhi | H299: Home & Kitchen | I299: Blender | J299: Same Day | K299: 4 | L299: 1121.04 | M299: 0.05 | N299: 4259.95 | O299: -394 | P299: =TEXT(B299,"mmm-yyyy") -> Jan-2024 | Q299: =IFERROR(O299/N299,"") -> -0.092489348 | R299: =IF(OR(N299>$U$3,N299<$U$2),"Sales Outlier",IF(OR(O299>$U$6,O299<$U$4),"Profit Outlier",""))
A300: ORD-100178 | B300: 45294 | D300: Amara Rossi | E300: Consumer | F300: South | G300: Hyderabad | H300: Furniture | I300: Dining Table | J300: First Class | K300: 2 | L300: 884.42 | M300: 0.15 | N300: 1503.51 | O300: -10.45 | P300: =TEXT(B300,"mmm-yyyy") -> Jan-2024 | Q300: =IFERROR(O300/N300,"") -> -0.0069504027 | R300: =IF(OR(N300>$U$3,N300<$U$2),"Sales Outlier",IF(OR(O300>$U$6,O300<$U$4),"Profit Outlier",""))
A301: ORD-100158 | B301: 45294 | D301: Unknown Customer | E301: Corporate | F301: West | G301: Pune | H301: Home & Kitchen | I301: Toaster | J301: Standard Class | K301: 2 | L301: 735.53 | M301: 0 | N301: 1471.06 | O301: 462.18 | P301: =TEXT(B301,"mmm-yyyy") -> Jan-2024 | Q301: =IFERROR(O301/N301,"") -> 0.31418161 | R301: =IF(OR(N301>$U$3,N301<$U$2),"Sales Outlier",IF(OR(O301>$U$6,O301<$U$4),"Profit Outlier",""))
A302: ORD-100036 | B302: 45294 | C302: 45507 | D302: Amara Rossi | E302: Corporate | F302: North | G302: Lucknow | H302: Furniture | I302: Sofa | J302: First Class | K302: 3 | L302: 613.1 | M302: 0.1 | N302: 1655.37 | O302: 213.06 | P302: =TEXT(B302,"mmm-yyyy") -> Jan-2024 | Q302: =IFERROR(O302/N302,"") -> 0.12870839 | R302: =IF(OR(N302>$U$3,N302<$U$2),"Sales Outlier",IF(OR(O302>$U$6,O302<$U$4),"Profit Outlier",""))
A303: ORD-100622 | B303: 45300 | C303: 45301 | D303: Wei Johnson | E303: Consumer | F303: South | G303: Bengaluru | H303: Furniture | I303: Dining Table | J303: Same Day | K303: 2 | L303: 1015.85 | M303: 0.15 | N303: 1726.94 | O303: -111.1 | P303: =TEXT(B303,"mmm-yyyy") -> Jan-2024 | Q303: =IFERROR(O303/N303,"") -> -0.064333445 | R303: =IF(OR(N303>$U$3,N303<$U$2),"Sales Outlier",IF(OR(O303>$U$6,O303<$U$4),"Profit Outlier",""))
A304: ORD-100177 | B304: 45301 | C304: 45305 | D304: Maria Said | E304: Unknown | F304: East | G304: Patna | H304: Home & Kitchen | I304: Air Fryer | J304: Same Day | K304: 2 | L304: 786.42 | M304: 0.05 | N304: 747.1 | O304: 96.89 | P304: =TEXT(B304,"mmm-yyyy") -> Jan-2024 | Q304: =IFERROR(O304/N304,"") -> 0.12968813 | R304: =IF(OR(N304>$U$3,N304<$U$2),"Sales Outlier",IF(OR(O304>$U$6,O304<$U$4),"Profit Outlier",""))
A305: ORD-100179 | B305: 45301 | C305: 45306 | D305: Anaya Chen | E305: Corporate | F305: East | G305: Patna | H305: Home & Kitchen | I305: Air Fryer | J305: Second Class | K305: 2 | L305: 455.11 | M305: 0.15 | N305: 773.69 | O305: 63.93 | P305: =TEXT(B305,"mmm-yyyy") -> Jan-2024 | Q305: =IFERROR(O305/N305,"") -> 0.082629994 | R305: =IF(OR(N305>$U$3,N305<$U$2),"Sales Outlier",IF(OR(O305>$U$6,O305<$U$4),"Profit Outlier",""))
A306: ORD-100635 | B306: 45302 | C306: 45308 | D306: Anaya Wang | E306: Corporate | F306: West | G306: Pune | H306: Furniture | I306: Office Chair | J306: Standard Class | K306: 2 | L306: 353.25 | M306: 0 | N306: 706.5 | O306: 34.31 | P306: =TEXT(B306,"mmm-yyyy") -> Jan-2024 | Q306: =IFERROR(O306/N306,"") -> 0.04856334 | R306: =IF(OR(N306>$U$3,N306<$U$2),"Sales Outlier",IF(OR(O306>$U$6,O306<$U$4),"Profit Outlier",""))
A307: ORD-100578 | B307: 45302 | C307: 45309 | D307: Ethan Petrov | E307: Home Office | F307: West | G307: Ahmedabad | H307: Clothing | I307: T-Shirt | J307: Standard Class | K307: 3 | L307: 837.74 | M307: 0.1 | N307: 2261.9 | O307: 40.07 | P307: =TEXT(B307,"mmm-yyyy") -> Jan-2024 | Q307: =IFERROR(O307/N307,"") -> 0.017715195 | R307: =IF(OR(N307>$U$3,N307<$U$2),"Sales Outlier",IF(OR(O307>$U$6,O307<$U$4),"Profit Outlier",""))
A308: ORD-100140 | B308: 45305 | C308: 45307 | D308: Liam Tanaka | E308: Home Office | F308: East | G308: Patna | H308: Electronics | I308: Bluetooth Speaker | J308: Standard Class | K308: 5 | L308: 225.93 | M308: 0.15 | N308: 960.2 | O308: -69.39 | P308: =TEXT(B308,"mmm-yyyy") -> Jan-2024 | Q308: =IFERROR(O308/N308,"") -> -0.072266195 | R308: =IF(OR(N308>$U$3,N308<$U$2),"Sales Outlier",IF(OR(O308>$U$6,O308<$U$4),"Profit Outlier",""))
A309: ORD-100150 | B309: 45307 | C309: 45310 | D309: Kenji Khan | E309: Consumer | F309: South | G309: Bengaluru | H309: Office Supplies | I309: Stapler | J309: Second Class | K309: 3 | L309: 507.46 | M309: 0.1 | N309: 1370.14 | O309: 411.37 | P309: =TEXT(B309,"mmm-yyyy") -> Jan-2024 | Q309: =IFERROR(O309/N309,"") -> 0.30023939 | R309: =IF(OR(N309>$U$3,N309<$U$2),"Sales Outlier",IF(OR(O309>$U$6,O309<$U$4),"Profit Outlier",""))
A310: ORD-100157 | B310: 45308 | C310: 45315 | D310: Fatima Fernandez | E310: Unknown | F310: East | G310: Patna | H310: Clothing | I310: Cap | J310: Same Day | K310: 3 | L310: 1054.78 | M310: 0 | N310: 3164.34 | O310: 894.88 | P310: =TEXT(B310,"mmm-yyyy") -> Jan-2024 | Q310: =IFERROR(O310/N310,"") -> 0.28280147 | R310: =IF(OR(N310>$U$3,N310<$U$2),"Sales Outlier",IF(OR(O310>$U$6,O310<$U$4),"Profit Outlier",""))
A311: ORD-100152 | B311: 45309 | C311: 45310 | D311: Maria Martin | E311: Corporate | F311: West | G311: Mumbai | H311: Clothing | I311: Sneakers | J311: First Class | K311: 1 | L311: 50.08 | M311: 0.05 | N311: 47.58 | O311: 10.09 | P311: =TEXT(B311,"mmm-yyyy") -> Jan-2024 | Q311: =IFERROR(O311/N311,"") -> 0.21206389 | R311: =IF(OR(N311>$U$3,N311<$U$2),"Sales Outlier",IF(OR(O311>$U$6,O311<$U$4),"Profit Outlier",""))
A312: ORD-100199 | B312: 45309 | C312: 45311 | D312: Nina Petrov | E312: Unknown | F312: North | G312: Chandigarh | H312: Clothing | I312: Jacket | J312: First Class | K312: 2 | L312: 957.14 | M312: 0.2 | N312: 1531.42 | O312: -1.12 | P312: =TEXT(B312,"mmm-yyyy") -> Jan-2024 | Q312: =IFERROR(O312/N312,"") -> -0.00073134738 | R312: =IF(OR(N312>$U$3,N312<$U$2),"Sales Outlier",IF(OR(O312>$U$6,O312<$U$4),"Profit Outlier",""))
A313: ORD-100086 | B313: 45309 | C313: 45313 | D313: Ivan Okafor | E313: Corporate | F313: South | G313: Chennai | H313: Furniture | I313: Sofa | J313: Second Class | K313: 2 | L313: 548.7 | M313: 0.2 | N313: 877.92 | O313: 180.99 | P313: =TEXT(B313,"mmm-yyyy") -> Jan-2024 | Q313: =IFERROR(O313/N313,"") -> 0.20615774 | R313: =IF(OR(N313>$U$3,N313<$U$2),"Sales Outlier",IF(OR(O313>$U$6,O313<$U$4),"Profit Outlier",""))
... A317: ORD-100137 | B317: 45314 | C317: 45317 | D317: Fatima Okafor | E317: Corporate | F317: West | G317: Mumbai | H317: Clothing | I317: Sneakers | J317: Second Class | K317: 2 | L317: 1062.04 | M317: 0.15 | N317: 1805.47 | O317: 233.22 | P317: =TEXT(B317,"mmm-yyyy") -> Jan-2024 | Q317: =IFERROR(O317/N317,"") -> 0.12917412 | R317: =IF(OR(N317>$U$3,N317<$U$2),"Sales Outlier",IF(OR(O317>$U$6,O317<$U$4),"Profit Outlier",""))
...

Sheet Summary
A1: Summary Tables (live formulas over Cleaned Data)
A3: Sales & Profit by Region
A4: Region | B4: Total Sales | C4: Total Profit | D4: Order Count | E4: Profit Margin %
A5: East | B5: =SUMIF('Cleaned Data'!$F:$F,A5,'Cleaned Data'!$N:$N) -> 191790.13 | C5: =SUMIF('Cleaned Data'!$F:$F,A5,'Cleaned Data'!$O:$O) -> 21881.09 | D5: =COUNTIF('Cleaned Data'!$F:$F,A5) -> 152 | E5: =IFERROR(C5/B5,"") -> 0.11408872
A6: North | B6: =SUMIF('Cleaned Data'!$F:$F,A6,'Cleaned Data'!$N:$N) -> 210985.61 | C6: =SUMIF('Cleaned Data'!$F:$F,A6,'Cleaned Data'!$O:$O) -> 20728.26 | D6: =COUNTIF('Cleaned Data'!$F:$F,A6) -> 141 | E6: =IFERROR(C6/B6,"") -> 0.098244899
A7: South | B7: =SUMIF('Cleaned Data'!$F:$F,A7,'Cleaned Data'!$N:$N) -> 208599.73 | C7: =SUMIF('Cleaned Data'!$F:$F,A7,'Cleaned Data'!$O:$O) -> 24978.92 | D7: =COUNTIF('Cleaned Data'!$F:$F,A7) -> 171 | E7: =IFERROR(C7/B7,"") -> 0.1197457
A8: West | B8: =SUMIF('Cleaned Data'!$F:$F,A8,'Cleaned Data'!$N:$N) -> 272527.89 | C8: =SUMIF('Cleaned Data'!$F:$F,A8,'Cleaned Data'!$O:$O) -> 34770.2 | D8: =COUNTIF('Cleaned Data'!$F:$F,A8) -> 186 | E8: =IFERROR(C8/B8,"") -> 0.12758401
A10: Sales & Profit by Category
A11: Category | B11: Total Sales | C11: Total Profit | D11: Order Count | E11: Profit Margin %
A12: Clothing | B12: =SUMIF('Cleaned Data'!$H:$H,A12,'Cleaned Data'!$N:$N) -> 165724.31 | C12: =SUMIF('Cleaned Data'!$H:$H,A12,'Cleaned Data'!$O:$O) -> 18533.6 | D12: =COUNTIF('Cleaned Data'!$H:$H,A12) -> 128 | E12: =IFERROR(C12/B12,"") -> 0.11183392
A13: Electronics | B13: =SUMIF('Cleaned Data'!$H:$H,A13,'Cleaned Data'!$N:$N) -> 192296.21 | C13: =SUMIF('Cleaned Data'!$H:$H,A13,'Cleaned Data'!$O:$O) -> 24954.71 | D13: =COUNTIF('Cleaned Data'!$H:$H,A13) -> 138 | E13: =IFERROR(C13/B13,"") -> 0.12977224
A14: Furniture | B14: =SUMIF('Cleaned Data'!$H:$H,A14,'Cleaned Data'!$N:$N) -> 180630.87 | C14: =SUMIF('Cleaned Data'!$H:$H,A14,'Cleaned Data'!$O:$O) -> 16382.72 | D14: =COUNTIF('Cleaned Data'!$H:$H,A14) -> 130 | E14: =IFERROR(C14/B14,"") -> 0.090697232
A15: Home & Kitchen | B15: =SUMIF('Cleaned Data'!$H:$H,A15,'Cleaned Data'!$N:$N) -> 190545.62 | C15: =SUMIF('Cleaned Data'!$H:$H,A15,'Cleaned Data'!$O:$O) -> 20397.9 | D15: =COUNTIF('Cleaned Data'!$H:$H,A15) -> 137 | E15: =IFERROR(C15/B15,"") -> 0.10704995
A16: Office Supplies | B16: =SUMIF('Cleaned Data'!$H:$H,A16,'Cleaned Data'!$N:$N) -> 154706.35 | C16: =SUMIF('Cleaned Data'!$H:$H,A16,'Cleaned Data'!$O:$O) -> 22089.54 | D16: =COUNTIF('Cleaned Data'!$H:$H,A16) -> 117 | E16: =IFERROR(C16/B16,"") -> 0.14278367
A18: Monthly Sales Trend
A19: Month | B19: Total Sales | C19: Total Profit
A20: Jan-2023 | B20: =SUMPRODUCT((TEXT('Cleaned Data'!$B$2:$B$651,"mmm-yyyy")=A20)*'Cleaned Data'!$N$2:$N$651) -> 40355.1 | C20: =SUMPRODUCT((TEXT('Cleaned Data'!$B$2:$B$651,"mmm-yyyy")=A20)*'Cleaned Data'!$O$2:$O$651) -> 4499.23
A21: Feb-2023 | B21: =SUMPRODUCT((TEXT('Cleaned Data'!$B$2:$B$651,"mmm-yyyy")=A21)*'Cleaned Data'!$N$2:$N$651) -> 40829.65 | C21: =SUMPRODUCT((TEXT('Cleaned Data'!$B$2:$B$651,"mmm-yyyy")=A21)*'Cleaned Data'!$O$2:$O$651) -> 3631.68
A22: Mar-2023 | B22: =SUMPRODUCT((TEXT('Cleaned Data'!$B$2:$B$651,"mmm-yyyy")=A22)*'Cleaned Data'!$N$2:$N$651) -> 44022.33 | C22: =SUMPRODUCT((TEXT('Cleaned Data'!$B$2:$B$651,"mmm-yyyy")=A22)*'Cleaned Data'!$O$2:$O$651) -> 4611.45
A23: Apr-2023 | B23: =SUMPRODUCT((TEXT('Cleaned Data'!$B$2:$B$651,"mmm-yyyy")=A23)*'Cleaned Data'!$N$2:$N$651) -> 23562.4 | C23: =SUMPRODUCT((TEXT('Cleaned Data'!$B$2:$B$651,"mmm-yyyy")=A23)*'Cleaned Data'!$O$2:$O$651) -> 2145.29
A24: May-2023 | B24: =SUMPRODUCT((TEXT('Cleaned Data'!$B$2:$B$651,"mmm-yyyy")=A24)*'Cleaned Data'!$N$2:$N$651) -> 37443.41 | C24: =SUMPRODUCT((TEXT('Cleaned Data'!$B$2:$B$651,"mmm-yyyy")=A24)*'Cleaned Data'!$O$2:$O$651) -> 6442.65
A25: Jun-2023 | B25: =SUMPRODUCT((TEXT('Cleaned Data'!$B$2:$B$651,"mmm-yyyy")=A25)*'Cleaned Data'!$N$2:$N$651) -> 16926.2 | C25: =SUMPRODUCT((TEXT('Cleaned Data'!$B$2:$B$651,"mmm-yyyy")=A25)*'Cleaned Data'!$O$2:$O$651) -> 2271.49
A26: Jul-2023 | B26: =SUMPRODUCT((TEXT('Cleaned Data'!$B$2:$B$651,"mmm-yyyy")=A26)*'Cleaned Data'!$N$2:$N$651) -> 36547.34 | C26: =SUMPRODUCT((TEXT('Cleaned Data'!$B$2:$B$651,"mmm-yyyy")=A26)*'Cleaned Data'!$O$2:$O$651) -> 5187.3
A27: Aug-2023 | B27: =SUMPRODUCT((TEXT('Cleaned Data'!$B$2:$B$651,"mmm-yyyy")=A27)*'Cleaned Data'!$N$2:$N$651) -> 25081.07 | C27: =SUMPRODUCT((TEXT('Cleaned Data'!$B$2:$B$651,"mmm-yyyy")=A27)*'Cleaned Data'!$O$2:$O$651) -> 4617.07
A28: Sep-2023 | B28: =SUMPRODUCT((TEXT('Cleaned Data'!$B$2:$B$651,"mmm-yyyy")=A28)*'Cleaned Data'!$N$2:$N$651) -> 20160.77 | C28: =SUMPRODUCT((TEXT('Cleaned Data'!$B$2:$B$651,"mmm-yyyy")=A28)*'Cleaned Data'!$O$2:$O$651) -> 1348.32
A29: Oct-2023 | B29: =SUMPRODUCT((TEXT('Cleaned Data'!$B$2:$B$651,"mmm-yyyy")=A29)*'Cleaned Data'!$N$2:$N$651) -> 47901.16 | C29: =SUMPRODUCT((TEXT('Cleaned Data'!$B$2:$B$651,"mmm-yyyy")=A29)*'Cleaned Data'!$O$2:$O$651) -> 5608.51
A30: Nov-2023 | B30: =SUMPRODUCT((TEXT('Cleaned Data'!$B$2:$B$651,"mmm-yyyy")=A30)*'Cleaned Data'!$N$2:$N$651) -> 40426.29 | C30: =SUMPRODUCT((TEXT('Cleaned Data'!$B$2:$B$651,"mmm-yyyy")=A30)*'Cleaned Data'!$O$2:$O$651) -> 4154.44
A31: Dec-2023 | B31: =SUMPRODUCT((TEXT('Cleaned Data'!$B$2:$B$651,"mmm-yyyy")=A31)*'Cleaned Data'!$N$2:$N$651) -> 29631.8 | C31: =SUMPRODUCT((TEXT('Cleaned Data'!$B$2:$B$651,"mmm-yyyy")=A31)*'Cleaned Data'!$O$2:$O$651) -> 4049.22
... A43: Dec-2024 | B43: =SUMPRODUCT((TEXT('Cleaned Data'!$B$2:$B$651,"mmm-yyyy")=A43)*'Cleaned Data'!$N$2:$N$651) -> 47673.25 | C43: =SUMPRODUCT((TEXT('Cleaned Data'!$B$2:$B$651,"mmm-yyyy")=A43)*'Cleaned Data'!$O$2:$O$651) -> 5879.85
A45: Segment Share of Sales
A46: Segment | B46: Total Sales | C46: % of Total Sales
A47: Consumer | B47: =SUMIF('Cleaned Data'!$E:$E,A47,'Cleaned Data'!$N:$N) -> 229370.52 | C47: =IFERROR(B47/$B$51,"") -> 0.25949728
A48: Corporate | B48: =SUMIF('Cleaned Data'!$E:$E,A48,'Cleaned Data'!$N:$N) -> 226808.75 | C48: =IFERROR(B48/$B$51,"") -> 0.25659904
A49: Home Office | B49: =SUMIF('Cleaned Data'!$E:$E,A49,'Cleaned Data'!$N:$N) -> 213297.21 | C49: =IFERROR(B49/$B$51,"") -> 0.24131282
A50: Unknown | B50: =SUMIF('Cleaned Data'!$E:$E,A50,'Cleaned Data'!$N:$N) -> 214426.88 | C50: =IFERROR(B50/$B$51,"") -> 0.24259086
A51: Total | B51: =SUM(B47:B50) -> 883903.36
A53: Top 10 Customers by Sales
A54: Customer Name | B54: Total Sales
A55: Noah Johnson | B55: =SUMIF('Cleaned Data'!$D:$D,A55,'Cleaned Data'!$N:$N) -> 9408.73
A56: Hassan Petrov | B56: =SUMIF('Cleaned Data'!$D:$D,A56,'Cleaned Data'!$N:$N) -> 9335.2
A57: Priya Rossi | B57: =SUMIF('Cleaned Data'!$D:$D,A57,'Cleaned Data'!$N:$N) -> 8840.77
A58: Yuki Chen | B58: =SUMIF('Cleaned Data'!$D:$D,A58,'Cleaned Data'!$N:$N) -> 8679.18
A59: Mei Brown | B59: =SUMIF('Cleaned Data'!$D:$D,A59,'Cleaned Data'!$N:$N) -> 8392.22
A60: Diego Okafor | B60: =SUMIF('Cleaned Data'!$D:$D,A60,'Cleaned Data'!$N:$N) -> 8343.56
A61: Priya Martin | B61: =SUMIF('Cleaned Data'!$D:$D,A61,'Cleaned Data'!$N:$N) -> 7921.94
A62: Hassan Okafor | B62: =SUMIF('Cleaned Data'!$D:$D,A62,'Cleaned Data'!$N:$N) -> 7769.61
A63: Kenji Ali | B63: =SUMIF('Cleaned Data'!$D:$D,A63,'Cleaned Data'!$N:$N) -> 7699.53
A64: Noah Sharma | B64: =SUMIF('Cleaned Data'!$D:$D,A64,'Cleaned Data'!$N:$N) -> 7665.85
